{
	"items": [{
		"type": -1,
		"cacheIndex": 0,
		"title": "时尚杂志模特 性感美女壁纸3",
		"markedTitle": "时尚杂志模特 性感美女壁纸3",
		"url": null,
		"summary": null,
		"markedSummary": null,
		"size": "192561",
		"date": null,
		"encoding": null,
		"time": 0,
		"docid": "f95ec8bcb552e502-6cd15eb3f19d6488-b8f9ee07e3a816b065493aae90419fc9",
		"debugInfo": null,
		"thumbUrl": "https://i01piccdn.sogoucdn.com/8f31f05f39cc13e8",
		"smallThumbUrl": "https://i01piccdn.sogoucdn.com/8f31f05f39cc13e8_tiny",
		"dataType": "pic",
		"page_url": "http://www.ivsky.com/photo/742/118644.html",
		"pic_url": "https://img.ivsky.com/Photo/UploadFiles/2008-6-10/200861023211786.jpg",
		"similarUrlFirst": null,
		"similarUrlSecond": null,
		"width": "1280",
		"height": "1024",
		"speedrank": null,
		"summarytype": "NormalSummary",
		"ori_pic_url": "http://img.ivsky.com/Photo/UploadFiles/2008-6-10/200861023211786.jpg",
		"https_convert": "1",
		"imgkey1": "03f83a0004491200",
		"imgkey2": "c5e14ef2843653ed",
		"imgcolor": "232",
		"hittag": "0",
		"thumb_width": "312",
		"thumb_height": "250",
		"anchor": null,
		"alt": null,
		"title2": null,
		"title1": "",
		"surr1": null,
		"surr2": "图片名称:时尚杂志模特-性感美女壁纸3 图片描述: 时尚杂志模特-性感美女壁纸",
		"summarypc": "0",
		"mf_id": "8f31f05f39cc13e8",
		"sohu_image": "",
		"lastmodified": "",
		"downloadPath": null,
		"downloadNum": null,
		"siteName": null,
		"anchor1": null,
		"grouppic": 0,
		"biaoqing": 0,
		"gifpic": 0,
		"ch_site_name": "天堂图片网",
		"grpdocs": null,
		"grpdata": null,
		"simdata": null,
		"feeddata": null,
		"gifdata": null,
		"pptdata": null,
		"pic_url_noredirect": "https://img.ivsky.com/Photo/UploadFiles/2008-6-10/200861023211786.jpg",
		"base_url": "",
		"groupid": null,
		"groupsize": 0,
		"easter": false,
		"easterUrl": null,
		"oriTitle": "时尚杂志模特 性感美女壁纸3",
		"showSnapShot": false,
		"normalSummary": true,
		"fastSummary": false,
		"allSummary": false,
		"ldata": "1522058209",
		"uri": ""
	}, {
		"type": -1,
		"cacheIndex": 1,
		"title": "韩国美女 刘寅娜",
		"markedTitle": "韩国美女 刘寅娜",
		"url": null,
		"summary": null,
		"markedSummary": null,
		"size": "649477",
		"date": null,
		"encoding": null,
		"time": 0,
		"docid": "6dfb2f34eed2f074-eb079ee68cf5a8cc-41048cbdf74b63da3958e57a95486865",
		"debugInfo": null,
		"thumbUrl": "https://i03piccdn.sogoucdn.com/e88863978c2eb013",
		"smallThumbUrl": "https://i03piccdn.sogoucdn.com/e88863978c2eb013_tiny",
		"dataType": "pic",
		"page_url": "http://bbs.hnol.net/mm/meinv-5780446-0-1.html",
		"pic_url": "http://image.hnol.net/c/2014-02/03/15/201402031551456661-2381913.jpg",
		"similarUrlFirst": null,
		"similarUrlSecond": null,
		"width": "1200",
		"height": "1920",
		"speedrank": null,
		"summarytype": "NormalSummary",
		"ori_pic_url": "http://image.hnol.net/c/2014-02/03/15/201402031551456661-2381913.jpg",
		"https_convert": "0",
		"imgkey1": "00e441ff024ac8e5",
		"imgkey2": "8bad3c9af1ff8670",
		"imgcolor": "192",
		"hittag": "0",
		"thumb_width": "250",
		"thumb_height": "399",
		"anchor": null,
		"alt": null,
		"title2": null,
		"title1": "",
		"surr1": null,
		"surr2": "",
		"summarypc": "0",
		"mf_id": "e88863978c2eb013",
		"sohu_image": "",
		"lastmodified": "",
		"downloadPath": null,
		"downloadNum": null,
		"siteName": null,
		"anchor1": null,
		"grouppic": 1,
		"biaoqing": 0,
		"gifpic": 0,
		"ch_site_name": "华声论坛",
		"grpdocs": null,
		"grpdata": null,
		"simdata": null,
		"feeddata": null,
		"gifdata": null,
		"pptdata": null,
		"pic_url_noredirect": "http://image.hnol.net/c/2014-02/03/15/201402031551456661-2381913.jpg",
		"base_url": "",
		"groupid": null,
		"groupsize": 0,
		"easter": false,
		"easterUrl": null,
		"oriTitle": "韩国美女 刘寅娜",
		"showSnapShot": false,
		"normalSummary": true,
		"fastSummary": false,
		"allSummary": false,
		"ldata": "1484233957",
		"uri": ""
	}, {
		"type": -1,
		"cacheIndex": 2,
		"title": "印度美女壁纸 第01辑",
		"markedTitle": "印度美女壁纸 第01辑",
		"url": null,
		"summary": null,
		"markedSummary": null,
		"size": "155040",
		"date": null,
		"encoding": null,
		"time": 0,
		"docid": "37e5193208fcc6bb-452dfeeeaabadb94-317d19d43bc71eca44b49ac643373259",
		"debugInfo": null,
		"thumbUrl": "https://i03piccdn.sogoucdn.com/b7d46f4bc47a492e",
		"smallThumbUrl": "https://i03piccdn.sogoucdn.com/b7d46f4bc47a492e_tiny",
		"dataType": "pic",
		"page_url": "http://article.pchome.net/content-403015.html",
		"pic_url": "http://img.article.pchome.net/00/22/72/35/pic_lib/wm/IndiaMM_1001.JPG",
		"similarUrlFirst": null,
		"similarUrlSecond": null,
		"width": "853",
		"height": "640",
		"speedrank": null,
		"summarytype": "NormalSummary",
		"ori_pic_url": "http://img.article.pchome.net/00/22/72/35/pic_lib/wm/IndiaMM_1001.JPG",
		"https_convert": "0",
		"imgkey1": "0230312505935b76",
		"imgkey2": "2bb451f67d5bdcb4",
		"imgcolor": "224",
		"hittag": "0",
		"thumb_width": "332",
		"thumb_height": "250",
		"anchor": null,
		"alt": null,
		"title2": null,
		"title1": "",
		"surr1": null,
		"surr2": "开始播放",
		"summarypc": "0",
		"mf_id": "b7d46f4bc47a492e",
		"sohu_image": "",
		"lastmodified": "",
		"downloadPath": null,
		"downloadNum": null,
		"siteName": null,
		"anchor1": null,
		"grouppic": 0,
		"biaoqing": 0,
		"gifpic": 0,
		"ch_site_name": "PCHOME",
		"grpdocs": null,
		"grpdata": null,
		"simdata": null,
		"feeddata": null,
		"gifdata": null,
		"pptdata": null,
		"pic_url_noredirect": "http://img.article.pchome.net/00/22/72/35/pic_lib/wm/IndiaMM_1001.JPG",
		"base_url": "",
		"groupid": null,
		"groupsize": 0,
		"easter": false,
		"easterUrl": null,
		"oriTitle": "印度美女壁纸 第01辑",
		"showSnapShot": false,
		"normalSummary": true,
		"fastSummary": false,
		"allSummary": false,
		"ldata": "0",
		"uri": ""
	}, {
		"type": -1,
		"cacheIndex": 3,
		"title": "美女图片",
		"markedTitle": "美女图片",
		"url": null,
		"summary": null,
		"markedSummary": null,
		"size": "93515",
		"date": null,
		"encoding": null,
		"time": 0,
		"docid": "ac75323d6b6de243-88c2ddd55cb8bca2-28213fcf11c3d69fce74fc27350502af",
		"debugInfo": null,
		"thumbUrl": "https://i04piccdn.sogoucdn.com/736e1ab2fa8bdce6",
		"smallThumbUrl": "https://i04piccdn.sogoucdn.com/736e1ab2fa8bdce6_tiny",
		"dataType": "pic",
		"page_url": "http://www.nipic.com/show/1/68/5708190k0e38ec12.html",
		"pic_url": "http://pic19.nipic.com/20120214/9191248_205117037000_2.jpg",
		"similarUrlFirst": null,
		"similarUrlSecond": null,
		"width": "681",
		"height": "1024",
		"speedrank": null,
		"summarytype": "NormalSummary",
		"ori_pic_url": "http://pic19.nipic.com/20120214/9191248_205117037000_2.jpg",
		"https_convert": "0",
		"imgkey1": "02d0197405d1b574",
		"imgkey2": "556b6854871e5bcb",
		"imgcolor": "74",
		"hittag": "0",
		"thumb_width": "250",
		"thumb_height": "376",
		"anchor": null,
		"alt": null,
		"title2": null,
		"title1": "",
		"surr1": null,
		"surr2": "",
		"summarypc": "0",
		"mf_id": "736e1ab2fa8bdce6",
		"sohu_image": "",
		"lastmodified": "",
		"downloadPath": null,
		"downloadNum": null,
		"siteName": null,
		"anchor1": null,
		"grouppic": 0,
		"biaoqing": 0,
		"gifpic": 0,
		"ch_site_name": "昵图网",
		"grpdocs": null,
		"grpdata": null,
		"simdata": null,
		"feeddata": null,
		"gifdata": null,
		"pptdata": null,
		"pic_url_noredirect": "http://pic19.nipic.com/20120214/9191248_205117037000_2.jpg",
		"base_url": "",
		"groupid": null,
		"groupsize": 0,
		"easter": false,
		"easterUrl": null,
		"oriTitle": "美女图片",
		"showSnapShot": false,
		"normalSummary": true,
		"fastSummary": false,
		"allSummary": false,
		"ldata": "1370593820",
		"uri": ""
	}, {
		"type": -1,
		"cacheIndex": 4,
		"title": "美女图片",
		"markedTitle": "美女图片",
		"url": null,
		"summary": null,
		"markedSummary": null,
		"size": "142229",
		"date": null,
		"encoding": null,
		"time": 0,
		"docid": "ac75323d6b6de243-174fbc37ffe7ed35-e262a1e9398dd87525dd341cf6d5f2ec",
		"debugInfo": null,
		"thumbUrl": "https://i02piccdn.sogoucdn.com/e203ce777c541cb4",
		"smallThumbUrl": "https://i02piccdn.sogoucdn.com/e203ce777c541cb4_tiny",
		"dataType": "pic",
		"page_url": "http://www.nipic.com/show/1/68/5533907kea819382.html",
		"pic_url": "http://pic18.nipic.com/20111221/8735627_110843652126_2.jpg",
		"similarUrlFirst": null,
		"similarUrlSecond": null,
		"width": "681",
		"height": "1024",
		"speedrank": null,
		"summarytype": "NormalSummary",
		"ori_pic_url": "http://pic18.nipic.com/20111221/8735627_110843652126_2.jpg",
		"https_convert": "0",
		"imgkey1": "012c37000302db92",
		"imgkey2": "899881b373b94c34",
		"imgcolor": "129",
		"hittag": "0",
		"thumb_width": "250",
		"thumb_height": "376",
		"anchor": null,
		"alt": null,
		"title2": null,
		"title1": "",
		"surr1": null,
		"surr2": "",
		"summarypc": "0",
		"mf_id": "e203ce777c541cb4",
		"sohu_image": "",
		"lastmodified": "",
		"downloadPath": null,
		"downloadNum": null,
		"siteName": null,
		"anchor1": null,
		"grouppic": 0,
		"biaoqing": 0,
		"gifpic": 0,
		"ch_site_name": "昵图网",
		"grpdocs": null,
		"grpdata": null,
		"simdata": null,
		"feeddata": null,
		"gifdata": null,
		"pptdata": null,
		"pic_url_noredirect": "http://pic18.nipic.com/20111221/8735627_110843652126_2.jpg",
		"base_url": "",
		"groupid": null,
		"groupsize": 0,
		"easter": false,
		"easterUrl": null,
		"oriTitle": "美女图片",
		"showSnapShot": false,
		"normalSummary": true,
		"fastSummary": false,
		"allSummary": false,
		"ldata": "1481167311",
		"uri": ""
	}, {
		"type": -1,
		"cacheIndex": 5,
		"title": "美体秀 29 Vicni",
		"markedTitle": "美体秀 29 Vicni",
		"url": null,
		"summary": null,
		"markedSummary": null,
		"size": "563786",
		"date": null,
		"encoding": null,
		"time": 0,
		"docid": "6dfb2f34eed2f074-eb079ee68cf5a8cc-fc37218eba3695d3c3c96bcb08d6270c",
		"debugInfo": null,
		"thumbUrl": "https://i04piccdn.sogoucdn.com/cb9ffea6da9f5cfc",
		"smallThumbUrl": "https://i04piccdn.sogoucdn.com/cb9ffea6da9f5cfc_tiny",
		"dataType": "pic",
		"page_url": "http://bbs.voc.com.cn/mm/meinv-7040015-15-1.html",
		"pic_url": "http://image.hnol.net/c/2016-03/03/18/20160303180846942-5058976.jpg",
		"similarUrlFirst": null,
		"similarUrlSecond": null,
		"width": "1066",
		"height": "1600",
		"speedrank": null,
		"summarytype": "NormalSummary",
		"ori_pic_url": "http://image.hnol.net/c/2016-03/03/18/20160303180846942-5058976.jpg",
		"https_convert": "0",
		"imgkey1": "00c03ac8056ec8c8",
		"imgkey2": "a554a6eb5af0a423",
		"imgcolor": "137",
		"hittag": "0",
		"thumb_width": "250",
		"thumb_height": "376",
		"anchor": null,
		"alt": null,
		"title2": null,
		"title1": "",
		"surr1": null,
		"surr2": "本帖助威记录",
		"summarypc": "0",
		"mf_id": "cb9ffea6da9f5cfc",
		"sohu_image": "",
		"lastmodified": "",
		"downloadPath": null,
		"downloadNum": null,
		"siteName": null,
		"anchor1": null,
		"grouppic": 0,
		"biaoqing": 0,
		"gifpic": 0,
		"ch_site_name": "华声论坛",
		"grpdocs": null,
		"grpdata": null,
		"simdata": null,
		"feeddata": null,
		"gifdata": null,
		"pptdata": null,
		"pic_url_noredirect": "http://image.hnol.net/c/2016-03/03/18/20160303180846942-5058976.jpg",
		"base_url": "",
		"groupid": null,
		"groupsize": 0,
		"easter": false,
		"easterUrl": null,
		"oriTitle": "美体秀 29 Vicni",
		"showSnapShot": false,
		"normalSummary": true,
		"fastSummary": false,
		"allSummary": false,
		"ldata": "1485324848",
		"uri": ""
	}, {
		"type": -1,
		"cacheIndex": 6,
		"title": "韩国美女曝靓照走红 网友称赞如真人版娜美",
		"markedTitle": "韩国美女曝靓照走红 网友称赞如真人版娜美",
		"url": null,
		"summary": null,
		"markedSummary": null,
		"size": "77533",
		"date": null,
		"encoding": null,
		"time": 0,
		"docid": "a6560b7a839a6988-32614d51ca28ff05-9f690b47d92490f366f26457beddecdd",
		"debugInfo": null,
		"thumbUrl": "https://i04piccdn.sogoucdn.com/aee7fc534ace717e",
		"smallThumbUrl": "https://i04piccdn.sogoucdn.com/aee7fc534ace717e_tiny",
		"dataType": "pic",
		"page_url": "http://society.eastday.com/s/20140523/u1a8106400.html",
		"pic_url": "https://bigtu.eastday.com/img/201405/23/30/5044797858266348302.jpg",
		"similarUrlFirst": null,
		"similarUrlSecond": null,
		"width": "530",
		"height": "819",
		"speedrank": null,
		"summarytype": "NormalSummary",
		"ori_pic_url": "http://bigtu.eastday.com/img/201405/23/30/5044797858266348302.jpg",
		"https_convert": "1",
		"imgkey1": "031035ff07fac9ff",
		"imgkey2": "544f7a0c87944bab",
		"imgcolor": "128",
		"hittag": "0",
		"thumb_width": "250",
		"thumb_height": "387",
		"anchor": null,
		"alt": null,
		"title2": null,
		"title1": "",
		"surr1": null,
		"surr2": "韩国女孩Minyoung Kim()日前因在网络上分享自己的美照而走红,被网友形容是\"既瘦又胸\",宛如《海贼王》(一部知名动漫)里人物\"娜美\"的真人翻版. 原标题: 韩国美女曝靓照走红 网友称赞如真人版娜美",
		"summarypc": "0",
		"mf_id": "aee7fc534ace717e",
		"sohu_image": "",
		"lastmodified": "",
		"downloadPath": null,
		"downloadNum": null,
		"siteName": null,
		"anchor1": null,
		"grouppic": 1,
		"biaoqing": 0,
		"gifpic": 0,
		"ch_site_name": "东方网",
		"grpdocs": null,
		"grpdata": null,
		"simdata": null,
		"feeddata": null,
		"gifdata": null,
		"pptdata": null,
		"pic_url_noredirect": "https://bigtu.eastday.com/img/201405/23/30/5044797858266348302.jpg",
		"base_url": "",
		"groupid": null,
		"groupsize": 0,
		"easter": false,
		"easterUrl": null,
		"oriTitle": "韩国美女曝靓照走红 网友称赞如真人版娜美",
		"showSnapShot": false,
		"normalSummary": true,
		"fastSummary": false,
		"allSummary": false,
		"ldata": "1529552088",
		"uri": ""
	}, {
		"type": -1,
		"cacheIndex": 7,
		"title": "俄罗斯美女",
		"markedTitle": "俄罗斯美女",
		"url": null,
		"summary": null,
		"markedSummary": null,
		"size": "86930",
		"date": null,
		"encoding": null,
		"time": 0,
		"docid": "95c435a20586d145-a2d99fe96884fa1b-4c7d2c5567170e9597948ab2786f0775",
		"debugInfo": null,
		"thumbUrl": "https://i02piccdn.sogoucdn.com/7093ca2f382bbeec",
		"smallThumbUrl": "https://i02piccdn.sogoucdn.com/7093ca2f382bbeec_tiny",
		"dataType": "pic",
		"page_url": "http://fashion.ifeng.com/listpage/photo/5985/4/klist.shtml",
		"pic_url": "https://d.ifengimg.com/mw600_mh625/y1.ifengimg.com/22435e07e492eaf0/2012/0703/rdn_4ff28e24eebbf.jpg",
		"similarUrlFirst": null,
		"similarUrlSecond": null,
		"width": "393",
		"height": "546",
		"speedrank": null,
		"summarytype": "NormalSummary",
		"ori_pic_url": "http://d.ifengimg.com/mw600_mh625/y1.ifengimg.com/22435e07e492eaf0/2012/0703/rdn_4ff28e24eebbf.jpg",
		"https_convert": "1",
		"imgkey1": "00e84122058e34e2",
		"imgkey2": "2c4f07a66e964533",
		"imgcolor": "131",
		"hittag": "0",
		"thumb_width": "263",
		"thumb_height": "366",
		"anchor": null,
		"alt": null,
		"title2": null,
		"title1": "",
		"surr1": null,
		"surr2": "在喷泉里戏水,玩水枪大战一直是俄罗斯美女酷爱的游戏,在这即将到来的炎炎夏日,也让我们一同感受下俄罗斯美女的清凉一刻.当然,这也绝对是一道最秀色可餐的俄罗斯风景线.... [查看全文]",
		"summarypc": "0",
		"mf_id": "7093ca2f382bbeec",
		"sohu_image": "",
		"lastmodified": "",
		"downloadPath": null,
		"downloadNum": null,
		"siteName": null,
		"anchor1": null,
		"grouppic": 0,
		"biaoqing": 0,
		"gifpic": 0,
		"ch_site_name": "凤凰时尚",
		"grpdocs": null,
		"grpdata": null,
		"simdata": null,
		"feeddata": null,
		"gifdata": null,
		"pptdata": null,
		"pic_url_noredirect": "https://d.ifengimg.com/mw600_mh625/y1.ifengimg.com/22435e07e492eaf0/2012/0703/rdn_4ff28e24eebbf.jpg",
		"base_url": "",
		"groupid": null,
		"groupsize": 0,
		"easter": false,
		"easterUrl": null,
		"oriTitle": "俄罗斯美女",
		"showSnapShot": false,
		"normalSummary": true,
		"fastSummary": false,
		"allSummary": false,
		"ldata": "1454674994",
		"uri": ""
	}, {
		"type": -1,
		"cacheIndex": 8,
		"title": "美女丝袜图片欧美女神壁纸高清大图预览1920x1080 美女壁纸下载",
		"markedTitle": "美女丝袜图片欧美女神壁纸高清大图预览1920x1080 美女壁纸下载",
		"url": null,
		"summary": null,
		"markedSummary": null,
		"size": "663812",
		"date": null,
		"encoding": null,
		"time": 0,
		"docid": "61782be166c826c8-653ea5468e5789eb-49abebfa1c43e97a4950ff89c98a28f0",
		"debugInfo": null,
		"thumbUrl": "https://i03piccdn.sogoucdn.com/2c87c18fb2aa333e",
		"smallThumbUrl": "https://i03piccdn.sogoucdn.com/2c87c18fb2aa333e_tiny",
		"dataType": "pic",
		"page_url": "http://www.win4000.com/wallpaper_big_44845_2.html",
		"pic_url": "http://pic1.win4000.com/wallpaper/1/531578e3ed79b.jpg",
		"similarUrlFirst": null,
		"similarUrlSecond": null,
		"width": "1200",
		"height": "800",
		"speedrank": null,
		"summarytype": "NormalSummary",
		"ori_pic_url": "http://pic1.win4000.com/wallpaper/1/531578e3ed79b.jpg",
		"https_convert": "0",
		"imgkey1": "04302400000112d2",
		"imgkey2": "0a3ff1963b4bd8ec",
		"imgcolor": "232",
		"hittag": "0",
		"thumb_width": "374",
		"thumb_height": "250",
		"anchor": null,
		"alt": null,
		"title2": null,
		"title1": "",
		"surr1": null,
		"surr2": "",
		"summarypc": "0",
		"mf_id": "2c87c18fb2aa333e",
		"sohu_image": "",
		"lastmodified": "",
		"downloadPath": null,
		"downloadNum": null,
		"siteName": null,
		"anchor1": null,
		"grouppic": 0,
		"biaoqing": 0,
		"gifpic": 0,
		"ch_site_name": "美桌网",
		"grpdocs": null,
		"grpdata": null,
		"simdata": null,
		"feeddata": null,
		"gifdata": null,
		"pptdata": null,
		"pic_url_noredirect": "http://pic1.win4000.com/wallpaper/1/531578e3ed79b.jpg",
		"base_url": "",
		"groupid": null,
		"groupsize": 0,
		"easter": false,
		"easterUrl": null,
		"oriTitle": "美女丝袜图片欧美女神壁纸高清大图预览1920x1080 美女壁纸下载",
		"showSnapShot": false,
		"normalSummary": true,
		"fastSummary": false,
		"allSummary": false,
		"ldata": "1513018071",
		"uri": ""
	}, {
		"type": -1,
		"cacheIndex": 9,
		"title": "广州某美女主播写真 组图",
		"markedTitle": "广州某美女主播写真 组图",
		"url": null,
		"summary": null,
		"markedSummary": null,
		"size": "77011",
		"date": null,
		"encoding": null,
		"time": 0,
		"docid": "6dfb2f34eed2f074-c16411bb98774d49-8681fde5714568d2fd10e8b16ef729d3",
		"debugInfo": null,
		"thumbUrl": "https://i03piccdn.sogoucdn.com/28ba837a2fb43501",
		"smallThumbUrl": "https://i03piccdn.sogoucdn.com/28ba837a2fb43501_tiny",
		"dataType": "pic",
		"page_url": "http://blog.sina.com.cn/s/blog_4bbfa8c7010007ck.html",
		"pic_url": "http://hs2.hnol.net/bbsimg/2006-4-4/9/200644922331050.jpg",
		"similarUrlFirst": null,
		"similarUrlSecond": null,
		"width": "740",
		"height": "1112",
		"speedrank": null,
		"summarytype": "NormalSummary",
		"ori_pic_url": "http://hs2.hnol.net/bbsimg/2006-4-4/9/200644922331050.jpg",
		"https_convert": "0",
		"imgkey1": "031821ff06b6c7ad",
		"imgkey2": "6272d6c40e6b34b8",
		"imgcolor": "0",
		"hittag": "0",
		"thumb_width": "250",
		"thumb_height": "376",
		"anchor": null,
		"alt": null,
		"title2": null,
		"title1": "",
		"surr1": null,
		"surr2": "",
		"summarypc": "0",
		"mf_id": "28ba837a2fb43501",
		"sohu_image": "",
		"lastmodified": "",
		"downloadPath": null,
		"downloadNum": null,
		"siteName": null,
		"anchor1": null,
		"grouppic": 1,
		"biaoqing": 0,
		"gifpic": 0,
		"ch_site_name": "新浪博客",
		"grpdocs": null,
		"grpdata": null,
		"simdata": null,
		"feeddata": null,
		"gifdata": null,
		"pptdata": null,
		"pic_url_noredirect": "http://hs2.hnol.net/bbsimg/2006-4-4/9/200644922331050.jpg",
		"base_url": "",
		"groupid": null,
		"groupsize": 0,
		"easter": false,
		"easterUrl": null,
		"oriTitle": "广州某美女主播写真 组图",
		"showSnapShot": false,
		"normalSummary": true,
		"fastSummary": false,
		"allSummary": false,
		"ldata": "1563167998",
		"uri": ""
	}, {
		"type": -1,
		"cacheIndex": 10,
		"title": "艾玛 沃特森性感美女桌面壁纸图片",
		"markedTitle": "艾玛 沃特森性感美女桌面壁纸图片",
		"url": null,
		"summary": null,
		"markedSummary": null,
		"size": "423391",
		"date": null,
		"encoding": null,
		"time": 0,
		"docid": "61782be166c826c8-653ea5468e5789eb-f99018fd6819df491f6d4166873f5d26",
		"debugInfo": null,
		"thumbUrl": "https://i02piccdn.sogoucdn.com/669cd47db6861598",
		"smallThumbUrl": "https://i02piccdn.sogoucdn.com/669cd47db6861598_tiny",
		"dataType": "pic",
		"page_url": "http://www.win4000.com/wallpaper_detail_99097.html",
		"pic_url": "http://pic1.win4000.com/wallpaper/d/56f11434662f0.jpg",
		"similarUrlFirst": null,
		"similarUrlSecond": null,
		"width": "1920",
		"height": "1080",
		"speedrank": null,
		"summarytype": "NormalSummary",
		"ori_pic_url": "http://pic1.win4000.com/wallpaper/d/56f11434662f0.jpg",
		"https_convert": "0",
		"imgkey1": "02a421e407b359e4",
		"imgkey2": "ad1e627e7ad3e9c7",
		"imgcolor": "128",
		"hittag": "0",
		"thumb_width": "446",
		"thumb_height": "249",
		"anchor": null,
		"alt": null,
		"title2": null,
		"title1": "",
		"surr1": null,
		"surr2": "",
		"summarypc": "0",
		"mf_id": "669cd47db6861598",
		"sohu_image": "",
		"lastmodified": "",
		"downloadPath": null,
		"downloadNum": null,
		"siteName": null,
		"anchor1": null,
		"grouppic": 0,
		"biaoqing": 0,
		"gifpic": 0,
		"ch_site_name": "美桌网",
		"grpdocs": null,
		"grpdata": null,
		"simdata": null,
		"feeddata": null,
		"gifdata": null,
		"pptdata": null,
		"pic_url_noredirect": "http://pic1.win4000.com/wallpaper/d/56f11434662f0.jpg",
		"base_url": "",
		"groupid": null,
		"groupsize": 0,
		"easter": false,
		"easterUrl": null,
		"oriTitle": "艾玛 沃特森性感美女桌面壁纸图片",
		"showSnapShot": false,
		"normalSummary": true,
		"fastSummary": false,
		"allSummary": false,
		"ldata": "1510548884",
		"uri": ""
	}, {
		"type": -1,
		"cacheIndex": 11,
		"title": "哪些星座喜欢挑战高难度爱情美女请注意",
		"markedTitle": "哪些星座喜欢挑战高难度爱情美女请注意",
		"url": null,
		"summary": null,
		"markedSummary": null,
		"size": "392766",
		"date": null,
		"encoding": null,
		"time": 0,
		"docid": "29db4d94382ad915-556a0d4ca03c0df6-e77f4e3bcd8ac10eed86e1514a6fe809",
		"debugInfo": null,
		"thumbUrl": "https://i03piccdn.sogoucdn.com/d83bfe9f9dbc08e3",
		"smallThumbUrl": "https://i03piccdn.sogoucdn.com/d83bfe9f9dbc08e3_tiny",
		"dataType": "pic",
		"page_url": "http://www.181010.com/mmw/1409.html",
		"pic_url": "http://www.181010.com/mmw/uploads/allimg/130621/2-1306212020013X.jpg",
		"similarUrlFirst": null,
		"similarUrlSecond": null,
		"width": "1920",
		"height": "1200",
		"speedrank": null,
		"summarytype": "NormalSummary",
		"ori_pic_url": "http://www.181010.com/mmw/uploads/allimg/130621/2-1306212020013X.jpg",
		"https_convert": "0",
		"imgkey1": "02343a00036da449",
		"imgkey2": "cd47adeb5a14a7c1",
		"imgcolor": "128",
		"hittag": "0",
		"thumb_width": "399",
		"thumb_height": "250",
		"anchor": null,
		"alt": null,
		"title2": null,
		"title1": "",
		"surr1": null,
		"surr2": "第三名、射手座:完全接受对方一切,尤其是小孩. 如果这个女生是离过婚,或是有带小孩,射手座会觉得:「这没有什麽,这OK,我本身就是很乐观的 星座 ,而且我很有爱心的.」其实他跟小孩的互动,一定要是小孩比较大了.如果这个小孩是在包尿布的阶段,或是",
		"summarypc": "0",
		"mf_id": "d83bfe9f9dbc08e3",
		"sohu_image": "",
		"lastmodified": "",
		"downloadPath": null,
		"downloadNum": null,
		"siteName": null,
		"anchor1": null,
		"grouppic": 0,
		"biaoqing": 0,
		"gifpic": 0,
		"ch_site_name": "",
		"grpdocs": null,
		"grpdata": null,
		"simdata": null,
		"feeddata": null,
		"gifdata": null,
		"pptdata": null,
		"pic_url_noredirect": "http://www.181010.com/mmw/uploads/allimg/130621/2-1306212020013X.jpg",
		"base_url": "",
		"groupid": null,
		"groupsize": 0,
		"easter": false,
		"easterUrl": null,
		"oriTitle": "哪些星座喜欢挑战高难度爱情美女请注意",
		"showSnapShot": false,
		"normalSummary": true,
		"fastSummary": false,
		"allSummary": false,
		"ldata": "1522550396",
		"uri": ""
	}, {
		"type": -1,
		"cacheIndex": 12,
		"title": "美女空姐图片",
		"markedTitle": "美女空姐图片",
		"url": null,
		"summary": null,
		"markedSummary": null,
		"size": "145446",
		"date": null,
		"encoding": null,
		"time": 0,
		"docid": "ac75323d6b6de243-2aa4c15053eeb353-c46d086ac5f609cdec4ee921c72dd6e0",
		"debugInfo": null,
		"thumbUrl": "https://i02piccdn.sogoucdn.com/2428cac090e2dcf8",
		"smallThumbUrl": "https://i02piccdn.sogoucdn.com/2428cac090e2dcf8_tiny",
		"dataType": "pic",
		"page_url": "http://www.nipic.com/show/1/68/9156910.html",
		"pic_url": "http://pic35.nipic.com/20131106/12151379_171636342183_2.jpg",
		"similarUrlFirst": null,
		"similarUrlSecond": null,
		"width": "1024",
		"height": "683",
		"speedrank": null,
		"summarytype": "NormalSummary",
		"ori_pic_url": "http://pic35.nipic.com/20131106/12151379_171636342183_2.jpg",
		"https_convert": "0",
		"imgkey1": "031c1fff07dbed64",
		"imgkey2": "d5c52e60a6b4034b",
		"imgcolor": "231",
		"hittag": "0",
		"thumb_width": "374",
		"thumb_height": "250",
		"anchor": null,
		"alt": null,
		"title2": null,
		"title1": "",
		"surr1": null,
		"surr2": "",
		"summarypc": "0",
		"mf_id": "2428cac090e2dcf8",
		"sohu_image": "",
		"lastmodified": "",
		"downloadPath": null,
		"downloadNum": null,
		"siteName": null,
		"anchor1": null,
		"grouppic": 0,
		"biaoqing": 0,
		"gifpic": 0,
		"ch_site_name": "昵图网",
		"grpdocs": null,
		"grpdata": null,
		"simdata": null,
		"feeddata": null,
		"gifdata": null,
		"pptdata": null,
		"pic_url_noredirect": "http://pic35.nipic.com/20131106/12151379_171636342183_2.jpg",
		"base_url": "",
		"groupid": null,
		"groupsize": 0,
		"easter": false,
		"easterUrl": null,
		"oriTitle": "美女空姐图片",
		"showSnapShot": false,
		"normalSummary": true,
		"fastSummary": false,
		"allSummary": false,
		"ldata": "1477200743",
		"uri": ""
	}, {
		"type": -1,
		"cacheIndex": 13,
		"title": "丝袜美女图片",
		"markedTitle": "丝袜美女图片",
		"url": null,
		"summary": null,
		"markedSummary": null,
		"size": "113702",
		"date": null,
		"encoding": null,
		"time": 0,
		"docid": "ac75323d6b6de243-a5e00022a0971b80-ece9e84c115c5c120f5efb839fa58a00",
		"debugInfo": null,
		"thumbUrl": "https://i03piccdn.sogoucdn.com/401b0204f51288ba",
		"smallThumbUrl": "https://i03piccdn.sogoucdn.com/401b0204f51288ba_tiny",
		"dataType": "pic",
		"page_url": "http://www.nipic.com/show/1/68/a5ad02de156f70ea.html",
		"pic_url": "http://pic5.nipic.com/20091231/1295091_134755472680_2.jpg",
		"similarUrlFirst": null,
		"similarUrlSecond": null,
		"width": "819",
		"height": "1024",
		"speedrank": null,
		"summarytype": "NormalSummary",
		"ori_pic_url": "http://pic5.nipic.com/20091231/1295091_134755472680_2.jpg",
		"https_convert": "0",
		"imgkey1": "055415ff07fe47b6",
		"imgkey2": "6a6ae64d8e46b6ba",
		"imgcolor": "231",
		"hittag": "0",
		"thumb_width": "250",
		"thumb_height": "311",
		"anchor": null,
		"alt": null,
		"title2": null,
		"title1": "",
		"surr1": null,
		"surr2": "",
		"summarypc": "0",
		"mf_id": "401b0204f51288ba",
		"sohu_image": "",
		"lastmodified": "",
		"downloadPath": null,
		"downloadNum": null,
		"siteName": null,
		"anchor1": null,
		"grouppic": 0,
		"biaoqing": 0,
		"gifpic": 0,
		"ch_site_name": "昵图网",
		"grpdocs": null,
		"grpdata": null,
		"simdata": null,
		"feeddata": null,
		"gifdata": null,
		"pptdata": null,
		"pic_url_noredirect": "http://pic5.nipic.com/20091231/1295091_134755472680_2.jpg",
		"base_url": "",
		"groupid": null,
		"groupsize": 0,
		"easter": false,
		"easterUrl": null,
		"oriTitle": "丝袜美女图片",
		"showSnapShot": false,
		"normalSummary": true,
		"fastSummary": false,
		"allSummary": false,
		"ldata": "1493227095",
		"uri": ""
	}, {
		"type": -1,
		"cacheIndex": 14,
		"title": "贺新年 美女高清内衣秀",
		"markedTitle": "贺新年 美女高清内衣秀",
		"url": null,
		"summary": null,
		"markedSummary": null,
		"size": "268004",
		"date": null,
		"encoding": null,
		"time": 0,
		"docid": "6dfb2f34eed2f074-eb079ee68cf5a8cc-43b234d573a343fc3f5ec299c3a335e3",
		"debugInfo": null,
		"thumbUrl": "https://i01piccdn.sogoucdn.com/912ae90eefa75f70",
		"smallThumbUrl": "https://i01piccdn.sogoucdn.com/912ae90eefa75f70_tiny",
		"dataType": "pic",
		"page_url": "http://bbs.voc.com.cn/mm/meinv-3960108-12-1.html",
		"pic_url": "http://image.hnol.net/c/2012-01/23/17/201201231752299431-2089977.jpg",
		"similarUrlFirst": null,
		"similarUrlSecond": null,
		"width": "1600",
		"height": "2391",
		"speedrank": null,
		"summarytype": "NormalSummary",
		"ori_pic_url": "http://image.hnol.net/c/2012-01/23/17/201201231752299431-2089977.jpg",
		"https_convert": "0",
		"imgkey1": "04f41dff07ffedff",
		"imgkey2": "7272f64c0f04c08c",
		"imgcolor": "231",
		"hittag": "0",
		"thumb_width": "254",
		"thumb_height": "380",
		"anchor": null,
		"alt": null,
		"title2": null,
		"title1": "",
		"surr1": null,
		"surr2": "",
		"summarypc": "0",
		"mf_id": "912ae90eefa75f70",
		"sohu_image": "",
		"lastmodified": "",
		"downloadPath": null,
		"downloadNum": null,
		"siteName": null,
		"anchor1": null,
		"grouppic": 0,
		"biaoqing": 0,
		"gifpic": 0,
		"ch_site_name": "华声论坛",
		"grpdocs": null,
		"grpdata": null,
		"simdata": null,
		"feeddata": null,
		"gifdata": null,
		"pptdata": null,
		"pic_url_noredirect": "http://image.hnol.net/c/2012-01/23/17/201201231752299431-2089977.jpg",
		"base_url": "",
		"groupid": null,
		"groupsize": 0,
		"easter": false,
		"easterUrl": null,
		"oriTitle": "贺新年 美女高清内衣秀",
		"showSnapShot": false,
		"normalSummary": true,
		"fastSummary": false,
		"allSummary": false,
		"ldata": "1493967451",
		"uri": ""
	}, {
		"type": -1,
		"cacheIndex": 15,
		"title": "美体秀 29 Vicni",
		"markedTitle": "美体秀 29 Vicni",
		"url": null,
		"summary": null,
		"markedSummary": null,
		"size": "489885",
		"date": null,
		"encoding": null,
		"time": 0,
		"docid": "6dfb2f34eed2f074-eb079ee68cf5a8cc-a08f5dca55849ce19bfbb0c8c8510a57",
		"debugInfo": null,
		"thumbUrl": "https://i02piccdn.sogoucdn.com/c0113ab52687c27d",
		"smallThumbUrl": "https://i02piccdn.sogoucdn.com/c0113ab52687c27d_tiny",
		"dataType": "pic",
		"page_url": "http://bbs.voc.com.cn/mm/meinv-7040015-15-1.html",
		"pic_url": "http://image.hnol.net/c/2016-03/03/18/201603031808487510-5058976.jpg",
		"similarUrlFirst": null,
		"similarUrlSecond": null,
		"width": "1066",
		"height": "1600",
		"speedrank": null,
		"summarytype": "NormalSummary",
		"ori_pic_url": "http://image.hnol.net/c/2016-03/03/18/201603031808487510-5058976.jpg",
		"https_convert": "0",
		"imgkey1": "014033b6034ac8db",
		"imgkey2": "aa18878f7a61b415",
		"imgcolor": "128",
		"hittag": "0",
		"thumb_width": "250",
		"thumb_height": "376",
		"anchor": null,
		"alt": null,
		"title2": null,
		"title1": "",
		"surr1": null,
		"surr2": "本帖助威记录",
		"summarypc": "0",
		"mf_id": "c0113ab52687c27d",
		"sohu_image": "",
		"lastmodified": "",
		"downloadPath": null,
		"downloadNum": null,
		"siteName": null,
		"anchor1": null,
		"grouppic": 0,
		"biaoqing": 0,
		"gifpic": 0,
		"ch_site_name": "华声论坛",
		"grpdocs": null,
		"grpdata": null,
		"simdata": null,
		"feeddata": null,
		"gifdata": null,
		"pptdata": null,
		"pic_url_noredirect": "http://image.hnol.net/c/2016-03/03/18/201603031808487510-5058976.jpg",
		"base_url": "",
		"groupid": null,
		"groupsize": 0,
		"easter": false,
		"easterUrl": null,
		"oriTitle": "美体秀 29 Vicni",
		"showSnapShot": false,
		"normalSummary": true,
		"fastSummary": false,
		"allSummary": false,
		"ldata": "1485324848",
		"uri": ""
	}, {
		"type": -1,
		"cacheIndex": 16,
		"title": "美女模特SISY性感写真 长腿美女长腿丝袜图片",
		"markedTitle": "美女模特SISY性感写真 长腿美女长腿丝袜图片",
		"url": null,
		"summary": null,
		"markedSummary": null,
		"size": "762277",
		"date": null,
		"encoding": null,
		"time": 0,
		"docid": "6dfb2f34eed2f074-eb079ee68cf5a8cc-d1af02b8663bf29814f4f87d6e3e520b",
		"debugInfo": null,
		"thumbUrl": "https://i01piccdn.sogoucdn.com/b043c310074208af",
		"smallThumbUrl": "https://i01piccdn.sogoucdn.com/b043c310074208af_tiny",
		"dataType": "pic",
		"page_url": "http://www.huaduw.com/thread-19182-1-1.html",
		"pic_url": "http://image.hnol.net/c/2015-10/18/14/20151018143510171-2089977.jpg",
		"similarUrlFirst": null,
		"similarUrlSecond": null,
		"width": "1600",
		"height": "2400",
		"speedrank": null,
		"summarytype": "NormalSummary",
		"ori_pic_url": "http://image.hnol.net/c/2015-10/18/14/20151018143510171-2089977.jpg",
		"https_convert": "0",
		"imgkey1": "011c3bff036edbb6",
		"imgkey2": "1a8b2a90fb594bdd",
		"imgcolor": "134",
		"hittag": "0",
		"thumb_width": "250",
		"thumb_height": "374",
		"anchor": null,
		"alt": null,
		"title2": null,
		"title1": "",
		"surr1": null,
		"surr2": "SISY思,内地平面模特,来自广东广州,秀人网新人,女神语录:我不是没脾气,只是不轻易发脾气…!.",
		"summarypc": "0",
		"mf_id": "b043c310074208af",
		"sohu_image": "",
		"lastmodified": "",
		"downloadPath": null,
		"downloadNum": null,
		"siteName": null,
		"anchor1": null,
		"grouppic": 0,
		"biaoqing": 0,
		"gifpic": 0,
		"ch_site_name": "华都网",
		"grpdocs": null,
		"grpdata": null,
		"simdata": null,
		"feeddata": null,
		"gifdata": null,
		"pptdata": null,
		"pic_url_noredirect": "http://image.hnol.net/c/2015-10/18/14/20151018143510171-2089977.jpg",
		"base_url": "",
		"groupid": null,
		"groupsize": 0,
		"easter": false,
		"easterUrl": null,
		"oriTitle": "美女模特SISY性感写真 长腿美女长腿丝袜图片",
		"showSnapShot": false,
		"normalSummary": true,
		"fastSummary": false,
		"allSummary": false,
		"ldata": "1489567047",
		"uri": ""
	}, {
		"type": -1,
		"cacheIndex": 17,
		"title": "最美混血美女泷泽萝拉",
		"markedTitle": "最美混血美女泷泽萝拉",
		"url": null,
		"summary": null,
		"markedSummary": null,
		"size": "90028",
		"date": null,
		"encoding": null,
		"time": 0,
		"docid": "b17c8f01e57d5969-eb03cac38a3679fc-130310b859e3b4590780fc424a2ca41b",
		"debugInfo": null,
		"thumbUrl": "https://i02piccdn.sogoucdn.com/772a6e28b6623665",
		"smallThumbUrl": "https://i02piccdn.sogoucdn.com/772a6e28b6623665_tiny",
		"dataType": "pic",
		"page_url": "http://lady.163.com/photoview/4CJ80026/24717.html",
		"pic_url": "https://img5.cache.netease.com/photo/0026/2012-07-12/867N3UVB4CJ80026.jpg",
		"similarUrlFirst": null,
		"similarUrlSecond": null,
		"width": "1280",
		"height": "720",
		"speedrank": null,
		"summarytype": "NormalSummary",
		"ori_pic_url": "http://img5.cache.netease.com/photo/0026/2012-07-12/867N3UVB4CJ80026.jpg",
		"https_convert": "1",
		"imgkey1": "01d42df604935bb5",
		"imgkey2": "93909dbff5db5c64",
		"imgcolor": "128",
		"hittag": "0",
		"thumb_width": "445",
		"thumb_height": "250",
		"anchor": null,
		"alt": null,
		"title2": null,
		"title1": "",
		"surr1": null,
		"surr2": "",
		"summarypc": "0",
		"mf_id": "772a6e28b6623665",
		"sohu_image": "",
		"lastmodified": "",
		"downloadPath": null,
		"downloadNum": null,
		"siteName": null,
		"anchor1": null,
		"grouppic": 0,
		"biaoqing": 0,
		"gifpic": 0,
		"ch_site_name": "网易女人",
		"grpdocs": null,
		"grpdata": null,
		"simdata": null,
		"feeddata": null,
		"gifdata": null,
		"pptdata": null,
		"pic_url_noredirect": "https://img5.cache.netease.com/photo/0026/2012-07-12/867N3UVB4CJ80026.jpg",
		"base_url": "",
		"groupid": null,
		"groupsize": 0,
		"easter": false,
		"easterUrl": null,
		"oriTitle": "最美混血美女泷泽萝拉",
		"showSnapShot": false,
		"normalSummary": true,
		"fastSummary": false,
		"allSummary": false,
		"ldata": "1414620816",
		"uri": ""
	}, {
		"type": -1,
		"cacheIndex": 18,
		"title": "全国各省第一美女出炉",
		"markedTitle": "全国各省第一美女出炉",
		"url": null,
		"summary": null,
		"markedSummary": null,
		"size": "40478",
		"date": null,
		"encoding": null,
		"time": 0,
		"docid": "a51423369a5d5a02-03f197e1a584bd04-636925764f5492f4321ae9755682f8ea",
		"debugInfo": null,
		"thumbUrl": "https://i01piccdn.sogoucdn.com/d895338ac3002a08",
		"smallThumbUrl": "https://i01piccdn.sogoucdn.com/d895338ac3002a08_tiny",
		"dataType": "pic",
		"page_url": "http://2008.163.com/07/1011/19/3QI1E47A0074250G.html",
		"pic_url": "https://cimg2.163.com/catchpic/9/9A/9A273EFDC89FE96B8D625973402D9F3E.jpg",
		"similarUrlFirst": null,
		"similarUrlSecond": null,
		"width": "500",
		"height": "588",
		"speedrank": null,
		"summarytype": "NormalSummary",
		"ori_pic_url": "http://cimg2.163.com/catchpic/9/9A/9A273EFDC89FE96B8D625973402D9F3E.jpg",
		"https_convert": "1",
		"imgkey1": "02d83fff07fec7b6",
		"imgkey2": "71eb7acc8754cb13",
		"imgcolor": "128",
		"hittag": "0",
		"thumb_width": "249",
		"thumb_height": "293",
		"anchor": null,
		"alt": null,
		"title2": null,
		"title1": "",
		"surr1": null,
		"surr2": "重庆——蒋勤勤 广东——蒙嘉慧 四川——张含韵 江苏——韩雪 浙江——周迅 江西——陈红 北京——高圆圆 上海——孙俪 天津——贾静雯",
		"summarypc": "0",
		"mf_id": "d895338ac3002a08",
		"sohu_image": "",
		"lastmodified": "",
		"downloadPath": null,
		"downloadNum": null,
		"siteName": null,
		"anchor1": null,
		"grouppic": 1,
		"biaoqing": 0,
		"gifpic": 0,
		"ch_site_name": "网易",
		"grpdocs": null,
		"grpdata": null,
		"simdata": null,
		"feeddata": null,
		"gifdata": null,
		"pptdata": null,
		"pic_url_noredirect": "https://cimg2.163.com/catchpic/9/9A/9A273EFDC89FE96B8D625973402D9F3E.jpg",
		"base_url": "",
		"groupid": null,
		"groupsize": 0,
		"easter": false,
		"easterUrl": null,
		"oriTitle": "全国各省第一美女出炉",
		"showSnapShot": false,
		"normalSummary": true,
		"fastSummary": false,
		"allSummary": false,
		"ldata": "1540676397",
		"uri": ""
	}, {
		"type": -1,
		"cacheIndex": 19,
		"title": "美女图片",
		"markedTitle": "美女图片",
		"url": null,
		"summary": null,
		"markedSummary": null,
		"size": "177088",
		"date": null,
		"encoding": null,
		"time": 0,
		"docid": "ac75323d6b6de243-d7d601aad05165f9-6aecae9a317de8a9783b8e447ea39314",
		"debugInfo": null,
		"thumbUrl": "https://i02piccdn.sogoucdn.com/19273a1dff9e5303",
		"smallThumbUrl": "https://i02piccdn.sogoucdn.com/19273a1dff9e5303_tiny",
		"dataType": "pic",
		"page_url": "http://www.nipic.com/show/1/68/8401593k5a20802a.html",
		"pic_url": "http://pic31.nipic.com/20130703/7447430_141620164000_2.jpg",
		"similarUrlFirst": null,
		"similarUrlSecond": null,
		"width": "683",
		"height": "1024",
		"speedrank": null,
		"summarytype": "NormalSummary",
		"ori_pic_url": "http://pic31.nipic.com/20130703/7447430_141620164000_2.jpg",
		"https_convert": "0",
		"imgkey1": "0144276d05b2dbff",
		"imgkey2": "0a3261863b49d894",
		"imgcolor": "128",
		"hittag": "0",
		"thumb_width": "250",
		"thumb_height": "374",
		"anchor": null,
		"alt": null,
		"title2": null,
		"title1": "",
		"surr1": null,
		"surr2": "",
		"summarypc": "0",
		"mf_id": "19273a1dff9e5303",
		"sohu_image": "",
		"lastmodified": "",
		"downloadPath": null,
		"downloadNum": null,
		"siteName": null,
		"anchor1": null,
		"grouppic": 0,
		"biaoqing": 0,
		"gifpic": 0,
		"ch_site_name": "昵图网",
		"grpdocs": null,
		"grpdata": null,
		"simdata": null,
		"feeddata": null,
		"gifdata": null,
		"pptdata": null,
		"pic_url_noredirect": "http://pic31.nipic.com/20130703/7447430_141620164000_2.jpg",
		"base_url": "",
		"groupid": null,
		"groupsize": 0,
		"easter": false,
		"easterUrl": null,
		"oriTitle": "美女图片",
		"showSnapShot": false,
		"normalSummary": true,
		"fastSummary": false,
		"allSummary": false,
		"ldata": "1476271937",
		"uri": ""
	}, {
		"type": -1,
		"cacheIndex": 20,
		"title": "乌克兰美女政客 裸照外泄,大方欣赏",
		"markedTitle": "乌克兰美女政客 裸照外泄,大方欣赏",
		"url": null,
		"summary": null,
		"markedSummary": null,
		"size": "178873",
		"date": null,
		"encoding": null,
		"time": 0,
		"docid": "c305b617fc2cf11a-cc4ddd7e6514166a-5da18cf1ca3331ed8847d893e6599d02",
		"debugInfo": null,
		"thumbUrl": "https://i02piccdn.sogoucdn.com/bf90245fb64049c7",
		"smallThumbUrl": "https://i02piccdn.sogoucdn.com/bf90245fb64049c7_tiny",
		"dataType": "pic",
		"page_url": "http://qnck.cyol.com/html/2014-10/08/nw.D110000qnck_20141008_2-44.htm",
		"pic_url": "http://qnck.cyol.com/images/2014-10/08/44/res19_attpic_brief.jpg",
		"similarUrlFirst": null,
		"similarUrlSecond": null,
		"width": "399",
		"height": "600",
		"speedrank": null,
		"summarytype": "NormalSummary",
		"ori_pic_url": "http://qnck.cyol.com/images/2014-10/08/44/res19_attpic_brief.jpg",
		"https_convert": "0",
		"imgkey1": "02682e01046eb68a",
		"imgkey2": "5d6fbfa192382b11",
		"imgcolor": "182",
		"hittag": "0",
		"thumb_width": "250",
		"thumb_height": "376",
		"anchor": null,
		"alt": null,
		"title2": null,
		"title1": "",
		"surr1": null,
		"surr2": "奥嘉对\"艳照外泄\"丝毫不在意,称这些照片堪称艺术品. 近日,美国好莱坞历史上最大的艳照外泄事件,仍在持续发酵.网上现已传出第四批女星裸照,著名内衣品牌\"维多利亚的秘密\"模特艾琳·希瑟顿、影星薇诺娜·瑞德、歌手英格丽·迈克尔森、《吸血鬼日记》演员妮娜·杜",
		"summarypc": "0",
		"mf_id": "bf90245fb64049c7",
		"sohu_image": "",
		"lastmodified": "",
		"downloadPath": null,
		"downloadNum": null,
		"siteName": null,
		"anchor1": null,
		"grouppic": 0,
		"biaoqing": 0,
		"gifpic": 0,
		"ch_site_name": "中青在线",
		"grpdocs": null,
		"grpdata": null,
		"simdata": null,
		"feeddata": null,
		"gifdata": null,
		"pptdata": null,
		"pic_url_noredirect": "http://qnck.cyol.com/images/2014-10/08/44/res19_attpic_brief.jpg",
		"base_url": "",
		"groupid": null,
		"groupsize": 0,
		"easter": false,
		"easterUrl": null,
		"oriTitle": "乌克兰美女政客 裸照外泄,大方欣赏",
		"showSnapShot": false,
		"normalSummary": true,
		"fastSummary": false,
		"allSummary": false,
		"ldata": "1413038956",
		"uri": ""
	}, {
		"type": -1,
		"cacheIndex": 21,
		"title": "性感美女诱惑床上照",
		"markedTitle": "性感美女诱惑床上照",
		"url": null,
		"summary": null,
		"markedSummary": null,
		"size": "39977",
		"date": null,
		"encoding": null,
		"time": 0,
		"docid": "d7036c9a17f5fda2-b25cc778cb5b7d1a-323166aa3a4480b51352cfb307720714",
		"debugInfo": null,
		"thumbUrl": "https://i02piccdn.sogoucdn.com/d503b3aa94185e66",
		"smallThumbUrl": "https://i02piccdn.sogoucdn.com/d503b3aa94185e66_tiny",
		"dataType": "pic",
		"page_url": "http://blog.sina.com.cn/s/blog_6a8fc0180100kpzc.html",
		"pic_url": "https://s5.sinaimg.cn/middle/6a8fc018g8ec5110f9824&690",
		"similarUrlFirst": null,
		"similarUrlSecond": null,
		"width": "461",
		"height": "690",
		"speedrank": null,
		"summarytype": "NormalSummary",
		"ori_pic_url": "http://s5.sinaimg.cn/middle/6a8fc018g8ec5110f9824&690",
		"https_convert": "1",
		"imgkey1": "04a01df507d7ebf5",
		"imgkey2": "1b6f316e7b14cf16",
		"imgcolor": "128",
		"hittag": "0",
		"thumb_width": "254",
		"thumb_height": "380",
		"anchor": null,
		"alt": null,
		"title2": null,
		"title1": "",
		"surr1": null,
		"surr2": "",
		"summarypc": "0",
		"mf_id": "d503b3aa94185e66",
		"sohu_image": "",
		"lastmodified": "",
		"downloadPath": null,
		"downloadNum": null,
		"siteName": null,
		"anchor1": null,
		"grouppic": 0,
		"biaoqing": 0,
		"gifpic": 0,
		"ch_site_name": "新浪博客",
		"grpdocs": null,
		"grpdata": null,
		"simdata": null,
		"feeddata": null,
		"gifdata": null,
		"pptdata": null,
		"pic_url_noredirect": "https://s5.sinaimg.cn/middle/6a8fc018g8ec5110f9824&690",
		"base_url": "",
		"groupid": null,
		"groupsize": 0,
		"easter": false,
		"easterUrl": null,
		"oriTitle": "性感美女诱惑床上照",
		"showSnapShot": false,
		"normalSummary": true,
		"fastSummary": false,
		"allSummary": false,
		"ldata": "1469941187",
		"uri": ""
	}, {
		"type": -1,
		"cacheIndex": 22,
		"title": "高清欧美美女图片",
		"markedTitle": "高清欧美美女图片",
		"url": null,
		"summary": null,
		"markedSummary": null,
		"size": "129620",
		"date": null,
		"encoding": null,
		"time": 0,
		"docid": "ac75323d6b6de243-23a9581ad20a0473-72da78efa64bc0ca27ade25ab7fef2a0",
		"debugInfo": null,
		"thumbUrl": "https://i03piccdn.sogoucdn.com/f7d97a5fb9b26794",
		"smallThumbUrl": "https://i03piccdn.sogoucdn.com/f7d97a5fb9b26794_tiny",
		"dataType": "pic",
		"page_url": "http://www.nipic.com/show/3566832.html",
		"pic_url": "http://pic9.nipic.com/20100822/5568954_101804065277_2.jpg",
		"similarUrlFirst": null,
		"similarUrlSecond": null,
		"width": "673",
		"height": "1024",
		"speedrank": null,
		"summarytype": "NormalSummary",
		"ori_pic_url": "http://pic9.nipic.com/20100822/5568954_101804065277_2.jpg",
		"https_convert": "0",
		"imgkey1": "01f41d6d05b6c96c",
		"imgkey2": "d54e7e688df683dd",
		"imgcolor": "128",
		"hittag": "0",
		"thumb_width": "250",
		"thumb_height": "380",
		"anchor": null,
		"alt": null,
		"title2": null,
		"title1": "",
		"surr1": null,
		"surr2": "",
		"summarypc": "0",
		"mf_id": "f7d97a5fb9b26794",
		"sohu_image": "",
		"lastmodified": "",
		"downloadPath": null,
		"downloadNum": null,
		"siteName": null,
		"anchor1": null,
		"grouppic": 0,
		"biaoqing": 0,
		"gifpic": 0,
		"ch_site_name": "昵图网",
		"grpdocs": null,
		"grpdata": null,
		"simdata": null,
		"feeddata": null,
		"gifdata": null,
		"pptdata": null,
		"pic_url_noredirect": "http://pic9.nipic.com/20100822/5568954_101804065277_2.jpg",
		"base_url": "",
		"groupid": null,
		"groupsize": 0,
		"easter": false,
		"easterUrl": null,
		"oriTitle": "高清欧美美女图片",
		"showSnapShot": false,
		"normalSummary": true,
		"fastSummary": false,
		"allSummary": false,
		"ldata": "1532291939",
		"uri": ""
	}, {
		"type": -1,
		"cacheIndex": 23,
		"title": "美女高清壁纸大图免费下载",
		"markedTitle": "美女高清壁纸大图免费下载",
		"url": null,
		"summary": null,
		"markedSummary": null,
		"size": "154441",
		"date": null,
		"encoding": null,
		"time": 0,
		"docid": "7376e62188f39519-7fa3883b011417ec-800f5322781f1dbd18b40b3beaaad6ab",
		"debugInfo": null,
		"thumbUrl": "https://i02piccdn.sogoucdn.com/a1aad70fc0749c38",
		"smallThumbUrl": "https://i02piccdn.sogoucdn.com/a1aad70fc0749c38_tiny",
		"dataType": "pic",
		"page_url": "http://www.mangowed.com/ipad/2015011710544.html",
		"pic_url": "http://www.mangowed.com/uploads/allimg/150117/1-15011H00UV95.jpg",
		"similarUrlFirst": null,
		"similarUrlSecond": null,
		"width": "1024",
		"height": "1024",
		"speedrank": null,
		"summarytype": "NormalSummary",
		"ori_pic_url": "http://www.mangowed.com/uploads/allimg/150117/1-15011H00UV95.jpg",
		"https_convert": "0",
		"imgkey1": "00a43524059237fe",
		"imgkey2": "4e13e2cc4b48deb3",
		"imgcolor": "128",
		"hittag": "0",
		"thumb_width": "255",
		"thumb_height": "255",
		"anchor": null,
		"alt": null,
		"title2": null,
		"title1": "",
		"surr1": null,
		"surr2": "",
		"summarypc": "0",
		"mf_id": "a1aad70fc0749c38",
		"sohu_image": "",
		"lastmodified": "",
		"downloadPath": null,
		"downloadNum": null,
		"siteName": null,
		"anchor1": null,
		"grouppic": 0,
		"biaoqing": 0,
		"gifpic": 0,
		"ch_site_name": "芒果唯美图片",
		"grpdocs": null,
		"grpdata": null,
		"simdata": null,
		"feeddata": null,
		"gifdata": null,
		"pptdata": null,
		"pic_url_noredirect": "http://www.mangowed.com/uploads/allimg/150117/1-15011H00UV95.jpg",
		"base_url": "",
		"groupid": null,
		"groupsize": 0,
		"easter": false,
		"easterUrl": null,
		"oriTitle": "美女高清壁纸大图免费下载",
		"showSnapShot": false,
		"normalSummary": true,
		"fastSummary": false,
		"allSummary": false,
		"ldata": "1518687491",
		"uri": ""
	}, {
		"type": -1,
		"cacheIndex": 24,
		"title": "萝莉美女图片",
		"markedTitle": "萝莉美女图片",
		"url": null,
		"summary": null,
		"markedSummary": null,
		"size": "499848",
		"date": null,
		"encoding": null,
		"time": 0,
		"docid": "ac75323d6b6de243-ff73e24afaeca590-a4d0f5c2ca845a7094e108e59ef99673",
		"debugInfo": null,
		"thumbUrl": "https://i01piccdn.sogoucdn.com/70666bffd843cefa",
		"smallThumbUrl": "https://i01piccdn.sogoucdn.com/70666bffd843cefa_tiny",
		"dataType": "pic",
		"page_url": "http://www.nipic.com/show/15367396.html",
		"pic_url": "http://pic105.nipic.com/file/20160726/10558867_171425363000_2.jpg",
		"similarUrlFirst": null,
		"similarUrlSecond": null,
		"width": "710",
		"height": "1024",
		"speedrank": null,
		"summarytype": "NormalSummary",
		"ori_pic_url": "http://pic105.nipic.com/file/20160726/10558867_171425363000_2.jpg",
		"https_convert": "0",
		"imgkey1": "008451ff058feb6d",
		"imgkey2": "0a14c9f77b79eeb5",
		"imgcolor": "221",
		"hittag": "0",
		"thumb_width": "250",
		"thumb_height": "360",
		"anchor": null,
		"alt": null,
		"title2": null,
		"title1": "",
		"surr1": null,
		"surr2": "",
		"summarypc": "0",
		"mf_id": "70666bffd843cefa",
		"sohu_image": "",
		"lastmodified": "",
		"downloadPath": null,
		"downloadNum": null,
		"siteName": null,
		"anchor1": null,
		"grouppic": 0,
		"biaoqing": 0,
		"gifpic": 0,
		"ch_site_name": "昵图网",
		"grpdocs": null,
		"grpdata": null,
		"simdata": null,
		"feeddata": null,
		"gifdata": null,
		"pptdata": null,
		"pic_url_noredirect": "http://pic105.nipic.com/file/20160726/10558867_171425363000_2.jpg",
		"base_url": "",
		"groupid": null,
		"groupsize": 0,
		"easter": false,
		"easterUrl": null,
		"oriTitle": "萝莉美女图片",
		"showSnapShot": false,
		"normalSummary": true,
		"fastSummary": false,
		"allSummary": false,
		"ldata": "1520500825",
		"uri": ""
	}, {
		"type": -1,
		"cacheIndex": 25,
		"title": "爱秀 9 2016 03 31 余菲菲Faye",
		"markedTitle": "爱秀 9 2016 03 31 余菲菲Faye",
		"url": null,
		"summary": null,
		"markedSummary": null,
		"size": "663604",
		"date": null,
		"encoding": null,
		"time": 0,
		"docid": "6dfb2f34eed2f074-eb079ee68cf5a8cc-f484100bba01345f9cf5c97920c080fa",
		"debugInfo": null,
		"thumbUrl": "https://i04piccdn.sogoucdn.com/d81d2dfdb3c2d846",
		"smallThumbUrl": "https://i04piccdn.sogoucdn.com/d81d2dfdb3c2d846_tiny",
		"dataType": "pic",
		"page_url": "http://bbs.voc.com.cn/mm/meinv-7088199-8-1.html",
		"pic_url": "http://image.hnol.net/c/2016-03/31/22/201603312216139373-5058976.jpg",
		"similarUrlFirst": null,
		"similarUrlSecond": null,
		"width": "1600",
		"height": "2401",
		"speedrank": null,
		"summarytype": "NormalSummary",
		"ori_pic_url": "http://image.hnol.net/c/2016-03/31/22/201603312216139373-5058976.jpg",
		"https_convert": "0",
		"imgkey1": "0184296306d9b7b6",
		"imgkey2": "5ce3726ce7d4dbc6",
		"imgcolor": "128",
		"hittag": "0",
		"thumb_width": "250",
		"thumb_height": "376",
		"anchor": null,
		"alt": null,
		"title2": null,
		"title1": "",
		"surr1": null,
		"surr2": "本帖助威记录",
		"summarypc": "0",
		"mf_id": "d81d2dfdb3c2d846",
		"sohu_image": "",
		"lastmodified": "",
		"downloadPath": null,
		"downloadNum": null,
		"siteName": null,
		"anchor1": null,
		"grouppic": 0,
		"biaoqing": 0,
		"gifpic": 0,
		"ch_site_name": "华声论坛",
		"grpdocs": null,
		"grpdata": null,
		"simdata": null,
		"feeddata": null,
		"gifdata": null,
		"pptdata": null,
		"pic_url_noredirect": "http://image.hnol.net/c/2016-03/31/22/201603312216139373-5058976.jpg",
		"base_url": "",
		"groupid": null,
		"groupsize": 0,
		"easter": false,
		"easterUrl": null,
		"oriTitle": "爱秀 9 2016 03 31 余菲菲Faye",
		"showSnapShot": false,
		"normalSummary": true,
		"fastSummary": false,
		"allSummary": false,
		"ldata": "1484389974",
		"uri": ""
	}, {
		"type": -1,
		"cacheIndex": 26,
		"title": "性感美女图片",
		"markedTitle": "性感美女图片",
		"url": null,
		"summary": null,
		"markedSummary": null,
		"size": "224818",
		"date": null,
		"encoding": null,
		"time": 0,
		"docid": "ac75323d6b6de243-cbe931c159ab22f1-bd951bbb770cd176288c9ca443ad7787",
		"debugInfo": null,
		"thumbUrl": "https://i03piccdn.sogoucdn.com/ec856f0c71004612",
		"smallThumbUrl": "https://i03piccdn.sogoucdn.com/ec856f0c71004612_tiny",
		"dataType": "pic",
		"page_url": "http://www.nipic.com/show/1/68/6694493k9df4e9a3.html",
		"pic_url": "http://pic23.nipic.com/20120813/7103350_071928800000_2.jpg",
		"similarUrlFirst": null,
		"similarUrlSecond": null,
		"width": "719",
		"height": "1024",
		"speedrank": null,
		"summarytype": "NormalSummary",
		"ori_pic_url": "http://pic23.nipic.com/20120813/7103350_071928800000_2.jpg",
		"https_convert": "0",
		"imgkey1": "00705f6b0466c763",
		"imgkey2": "b2bae8957d43789c",
		"imgcolor": "167",
		"hittag": "0",
		"thumb_width": "250",
		"thumb_height": "355",
		"anchor": null,
		"alt": null,
		"title2": null,
		"title1": "",
		"surr1": null,
		"surr2": "",
		"summarypc": "0",
		"mf_id": "ec856f0c71004612",
		"sohu_image": "",
		"lastmodified": "",
		"downloadPath": null,
		"downloadNum": null,
		"siteName": null,
		"anchor1": null,
		"grouppic": 0,
		"biaoqing": 0,
		"gifpic": 0,
		"ch_site_name": "昵图网",
		"grpdocs": null,
		"grpdata": null,
		"simdata": null,
		"feeddata": null,
		"gifdata": null,
		"pptdata": null,
		"pic_url_noredirect": "http://pic23.nipic.com/20120813/7103350_071928800000_2.jpg",
		"base_url": "",
		"groupid": null,
		"groupsize": 0,
		"easter": false,
		"easterUrl": null,
		"oriTitle": "性感美女图片",
		"showSnapShot": false,
		"normalSummary": true,
		"fastSummary": false,
		"allSummary": false,
		"ldata": "1469595751",
		"uri": ""
	}, {
		"type": -1,
		"cacheIndex": 27,
		"title": "性感内衣美女图片",
		"markedTitle": "性感内衣美女图片",
		"url": null,
		"summary": null,
		"markedSummary": null,
		"size": "84501",
		"date": null,
		"encoding": null,
		"time": 0,
		"docid": "ac75323d6b6de243-4ae01c7db4cb0b81-212e2307eba2a6c4a84f18bf6a918351",
		"debugInfo": null,
		"thumbUrl": "https://i01piccdn.sogoucdn.com/d6979ad28ad24b4b",
		"smallThumbUrl": "https://i01piccdn.sogoucdn.com/d6979ad28ad24b4b_tiny",
		"dataType": "pic",
		"page_url": "http://www.nipic.com/show/4225755.html",
		"pic_url": "http://pic12.nipic.com/20110213/5684178_020621573000_2.jpg",
		"similarUrlFirst": null,
		"similarUrlSecond": null,
		"width": "683",
		"height": "1024",
		"speedrank": null,
		"summarytype": "NormalSummary",
		"ori_pic_url": "http://pic12.nipic.com/20110213/5684178_020621573000_2.jpg",
		"https_convert": "0",
		"imgkey1": "04e419fe07fb6bfe",
		"imgkey2": "6267ee4d8e44b6ea",
		"imgcolor": "231",
		"hittag": "0",
		"thumb_width": "250",
		"thumb_height": "374",
		"anchor": null,
		"alt": null,
		"title2": null,
		"title1": "",
		"surr1": null,
		"surr2": "",
		"summarypc": "0",
		"mf_id": "d6979ad28ad24b4b",
		"sohu_image": "",
		"lastmodified": "",
		"downloadPath": null,
		"downloadNum": null,
		"siteName": null,
		"anchor1": null,
		"grouppic": 0,
		"biaoqing": 0,
		"gifpic": 0,
		"ch_site_name": "昵图网",
		"grpdocs": null,
		"grpdata": null,
		"simdata": null,
		"feeddata": null,
		"gifdata": null,
		"pptdata": null,
		"pic_url_noredirect": "http://pic12.nipic.com/20110213/5684178_020621573000_2.jpg",
		"base_url": "",
		"groupid": null,
		"groupsize": 0,
		"easter": false,
		"easterUrl": null,
		"oriTitle": "性感内衣美女图片",
		"showSnapShot": false,
		"normalSummary": true,
		"fastSummary": false,
		"allSummary": false,
		"ldata": "1514201662",
		"uri": ""
	}, {
		"type": -1,
		"cacheIndex": 28,
		"title": "美女图图片",
		"markedTitle": "美女图图片",
		"url": null,
		"summary": null,
		"markedSummary": null,
		"size": "104175",
		"date": null,
		"encoding": null,
		"time": 0,
		"docid": "ac75323d6b6de243-a58ff320b7144183-3558ff4cbec7f448dcddb2ce9ba304e5",
		"debugInfo": null,
		"thumbUrl": "https://i01piccdn.sogoucdn.com/d40ee0cef02a634c",
		"smallThumbUrl": "https://i01piccdn.sogoucdn.com/d40ee0cef02a634c_tiny",
		"dataType": "pic",
		"page_url": "http://www.nipic.com/show/1/68/8344211kbe518c0f.html",
		"pic_url": "http://pic30.nipic.com/20130624/2929309_152254606101_2.jpg",
		"similarUrlFirst": null,
		"similarUrlSecond": null,
		"width": "683",
		"height": "1024",
		"speedrank": null,
		"summarytype": "NormalSummary",
		"ori_pic_url": "http://pic30.nipic.com/20130624/2929309_152254606101_2.jpg",
		"https_convert": "0",
		"imgkey1": "051817ff07ffe9fe",
		"imgkey2": "6a72665c0f00b39a",
		"imgcolor": "231",
		"hittag": "0",
		"thumb_width": "250",
		"thumb_height": "374",
		"anchor": null,
		"alt": null,
		"title2": null,
		"title1": "",
		"surr1": null,
		"surr2": "",
		"summarypc": "0",
		"mf_id": "d40ee0cef02a634c",
		"sohu_image": "",
		"lastmodified": "",
		"downloadPath": null,
		"downloadNum": null,
		"siteName": null,
		"anchor1": null,
		"grouppic": 0,
		"biaoqing": 0,
		"gifpic": 0,
		"ch_site_name": "昵图网",
		"grpdocs": null,
		"grpdata": null,
		"simdata": null,
		"feeddata": null,
		"gifdata": null,
		"pptdata": null,
		"pic_url_noredirect": "http://pic30.nipic.com/20130624/2929309_152254606101_2.jpg",
		"base_url": "",
		"groupid": null,
		"groupsize": 0,
		"easter": false,
		"easterUrl": null,
		"oriTitle": "美女图图片",
		"showSnapShot": false,
		"normalSummary": true,
		"fastSummary": false,
		"allSummary": false,
		"ldata": "1471064724",
		"uri": ""
	}, {
		"type": -1,
		"cacheIndex": 29,
		"title": "大美女林志玲",
		"markedTitle": "大美女林志玲",
		"url": null,
		"summary": null,
		"markedSummary": null,
		"size": "103431",
		"date": null,
		"encoding": null,
		"time": 0,
		"docid": "f88fca9df87dc641-cdb4ea9a10a24600-e7e1c79cc1ffa0284eb8a1af96488c40",
		"debugInfo": null,
		"thumbUrl": "https://i01piccdn.sogoucdn.com/a8f8328c122b6fa7",
		"smallThumbUrl": "https://i01piccdn.sogoucdn.com/a8f8328c122b6fa7_tiny",
		"dataType": "pic",
		"page_url": "http://www.tooopen.com/view/1130748.html",
		"pic_url": "http://img02.tooopen.com/images/20160407/tooopen_sy_158600838982.jpg",
		"similarUrlFirst": null,
		"similarUrlSecond": null,
		"width": "720",
		"height": "1015",
		"speedrank": null,
		"summarytype": "NormalSummary",
		"ori_pic_url": "http://img02.tooopen.com/images/20160407/tooopen_sy_158600838982.jpg",
		"https_convert": "0",
		"imgkey1": "027822090371b69b",
		"imgkey2": "848d706a8fd4caec",
		"imgcolor": "192",
		"hittag": "0",
		"thumb_width": "249",
		"thumb_height": "352",
		"anchor": null,
		"alt": null,
		"title2": null,
		"title1": "",
		"surr1": null,
		"surr2": "",
		"summarypc": "0",
		"mf_id": "a8f8328c122b6fa7",
		"sohu_image": "",
		"lastmodified": "",
		"downloadPath": null,
		"downloadNum": null,
		"siteName": null,
		"anchor1": null,
		"grouppic": 0,
		"biaoqing": 0,
		"gifpic": 0,
		"ch_site_name": "素材公社",
		"grpdocs": null,
		"grpdata": null,
		"simdata": null,
		"feeddata": null,
		"gifdata": null,
		"pptdata": null,
		"pic_url_noredirect": "http://img02.tooopen.com/images/20160407/tooopen_sy_158600838982.jpg",
		"base_url": "",
		"groupid": null,
		"groupsize": 0,
		"easter": false,
		"easterUrl": null,
		"oriTitle": "大美女林志玲",
		"showSnapShot": false,
		"normalSummary": true,
		"fastSummary": false,
		"allSummary": false,
		"ldata": "1526865594",
		"uri": ""
	}, {
		"type": -1,
		"cacheIndex": 30,
		"title": "永远的美女",
		"markedTitle": "永远的美女",
		"url": null,
		"summary": null,
		"markedSummary": null,
		"size": "302759",
		"date": null,
		"encoding": null,
		"time": 0,
		"docid": "6dfb2f34eed2f074-eb079ee68cf5a8cc-2224efa9ef03a523ba0835abf4176073",
		"debugInfo": null,
		"thumbUrl": "https://i04piccdn.sogoucdn.com/d8bdb431b62b5558",
		"smallThumbUrl": "https://i04piccdn.sogoucdn.com/d8bdb431b62b5558_tiny",
		"dataType": "pic",
		"page_url": "http://bbs.voc.com.cn/mm/meinv-3926154-7-1.html",
		"pic_url": "http://image.hnol.net/c/2012-01/04/10/201201041024158671-1988454.jpg",
		"similarUrlFirst": null,
		"similarUrlSecond": null,
		"width": "1500",
		"height": "2162",
		"speedrank": null,
		"summarytype": "NormalSummary",
		"ori_pic_url": "http://image.hnol.net/c/2012-01/04/10/201201041024158671-1988454.jpg",
		"https_convert": "0",
		"imgkey1": "030c1dff06b6496e",
		"imgkey2": "42697cfa858c9662",
		"imgcolor": "231",
		"hittag": "0",
		"thumb_width": "259",
		"thumb_height": "373",
		"anchor": null,
		"alt": null,
		"title2": null,
		"title1": "",
		"surr1": null,
		"surr2": "",
		"summarypc": "0",
		"mf_id": "d8bdb431b62b5558",
		"sohu_image": "",
		"lastmodified": "",
		"downloadPath": null,
		"downloadNum": null,
		"siteName": null,
		"anchor1": null,
		"grouppic": 0,
		"biaoqing": 0,
		"gifpic": 0,
		"ch_site_name": "华声论坛",
		"grpdocs": null,
		"grpdata": null,
		"simdata": null,
		"feeddata": null,
		"gifdata": null,
		"pptdata": null,
		"pic_url_noredirect": "http://image.hnol.net/c/2012-01/04/10/201201041024158671-1988454.jpg",
		"base_url": "",
		"groupid": null,
		"groupsize": 0,
		"easter": false,
		"easterUrl": null,
		"oriTitle": "永远的美女",
		"showSnapShot": false,
		"normalSummary": true,
		"fastSummary": false,
		"allSummary": false,
		"ldata": "1487731615",
		"uri": ""
	}, {
		"type": -1,
		"cacheIndex": 31,
		"title": "丝袜美女桌面壁纸之性感的学生妹子高清大图预览1920 1200 美女壁纸下载",
		"markedTitle": "丝袜美女桌面壁纸之性感的学生妹子高清大图预览1920 1200 美女壁纸下载",
		"url": null,
		"summary": null,
		"markedSummary": null,
		"size": "442515",
		"date": null,
		"encoding": null,
		"time": 0,
		"docid": "61782be166c826c8-653ea5468e5789eb-593bf9cb17f343cf17afe940dc2b6981",
		"debugInfo": null,
		"thumbUrl": "https://i04piccdn.sogoucdn.com/c50fbe926441af2a",
		"smallThumbUrl": "https://i04piccdn.sogoucdn.com/c50fbe926441af2a_tiny",
		"dataType": "pic",
		"page_url": "http://www.win4000.com/wallpaper_big_38855.html",
		"pic_url": "http://pic1.win4000.com/wallpaper/1/51aeb1737b741.jpg",
		"similarUrlFirst": null,
		"similarUrlSecond": null,
		"width": "1920",
		"height": "1200",
		"speedrank": null,
		"summarytype": "NormalSummary",
		"ori_pic_url": "http://pic1.win4000.com/wallpaper/1/51aeb1737b741.jpg",
		"https_convert": "0",
		"imgkey1": "01e0340001251564",
		"imgkey2": "7a3ae01c3b4b549e",
		"imgcolor": "128",
		"hittag": "0",
		"thumb_width": "404",
		"thumb_height": "250",
		"anchor": null,
		"alt": null,
		"title2": null,
		"title1": "",
		"surr1": null,
		"surr2": "",
		"summarypc": "0",
		"mf_id": "c50fbe926441af2a",
		"sohu_image": "",
		"lastmodified": "",
		"downloadPath": null,
		"downloadNum": null,
		"siteName": null,
		"anchor1": null,
		"grouppic": 0,
		"biaoqing": 0,
		"gifpic": 0,
		"ch_site_name": "美桌网",
		"grpdocs": null,
		"grpdata": null,
		"simdata": null,
		"feeddata": null,
		"gifdata": null,
		"pptdata": null,
		"pic_url_noredirect": "http://pic1.win4000.com/wallpaper/1/51aeb1737b741.jpg",
		"base_url": "",
		"groupid": null,
		"groupsize": 0,
		"easter": false,
		"easterUrl": null,
		"oriTitle": "丝袜美女桌面壁纸之性感的学生妹子高清大图预览1920 1200 美女壁纸下载",
		"showSnapShot": false,
		"normalSummary": true,
		"fastSummary": false,
		"allSummary": false,
		"ldata": "1515311124",
		"uri": ""
	}, {
		"type": -1,
		"cacheIndex": 32,
		"title": "成熟性感美女广告模特 孟茜大胆写真",
		"markedTitle": "成熟性感美女广告模特 孟茜大胆写真",
		"url": null,
		"summary": null,
		"markedSummary": null,
		"size": "54184",
		"date": null,
		"encoding": null,
		"time": 0,
		"docid": "f88fca9df87dc641-a01b26ff678c8216-8a15ac4c04ff15dc6edf8246d6f4fe0f",
		"debugInfo": null,
		"thumbUrl": "https://i01piccdn.sogoucdn.com/338f39d09221afd2",
		"smallThumbUrl": "https://i01piccdn.sogoucdn.com/338f39d09221afd2_tiny",
		"dataType": "pic",
		"page_url": "http://www.tooopen.com/view/134120.html",
		"pic_url": "http://img01.tooopen.com/Downs/images/2010/12/26/sy_201012261442173030-1.jpg",
		"similarUrlFirst": null,
		"similarUrlSecond": null,
		"width": "682",
		"height": "1024",
		"speedrank": null,
		"summarytype": "NormalSummary",
		"ori_pic_url": "http://img01.tooopen.com/Downs/images/2010/12/26/sy_201012261442173030-1.jpg",
		"https_convert": "0",
		"imgkey1": "016c256e05b64724",
		"imgkey2": "2f5c8559388ba62a",
		"imgcolor": "128",
		"hittag": "0",
		"thumb_width": "250",
		"thumb_height": "376",
		"anchor": null,
		"alt": null,
		"title2": null,
		"title1": "",
		"surr1": null,
		"surr2": "成熟性感美女广告模特--孟茜大胆写真",
		"summarypc": "0",
		"mf_id": "338f39d09221afd2",
		"sohu_image": "",
		"lastmodified": "",
		"downloadPath": null,
		"downloadNum": null,
		"siteName": null,
		"anchor1": null,
		"grouppic": 0,
		"biaoqing": 0,
		"gifpic": 0,
		"ch_site_name": "素材公社",
		"grpdocs": null,
		"grpdata": null,
		"simdata": null,
		"feeddata": null,
		"gifdata": null,
		"pptdata": null,
		"pic_url_noredirect": "http://img01.tooopen.com/Downs/images/2010/12/26/sy_201012261442173030-1.jpg",
		"base_url": "",
		"groupid": null,
		"groupsize": 0,
		"easter": false,
		"easterUrl": null,
		"oriTitle": "成熟性感美女广告模特 孟茜大胆写真",
		"showSnapShot": false,
		"normalSummary": true,
		"fastSummary": false,
		"allSummary": false,
		"ldata": "1527230646",
		"uri": ""
	}, {
		"type": -1,
		"cacheIndex": 33,
		"title": "美女御姐顾欣怡清凉透视装",
		"markedTitle": "美女御姐顾欣怡清凉透视装",
		"url": null,
		"summary": null,
		"markedSummary": null,
		"size": "106926",
		"date": null,
		"encoding": null,
		"time": 0,
		"docid": "f9850dbf9318c096-5acef2f2c720b01b-fdbc5f63356e4e65259f127942a46273",
		"debugInfo": null,
		"thumbUrl": "https://i02piccdn.sogoucdn.com/b0ab029bc46a1944",
		"smallThumbUrl": "https://i02piccdn.sogoucdn.com/b0ab029bc46a1944_tiny",
		"dataType": "pic",
		"page_url": "http://tt.mop.com/15377714.html",
		"pic_url": "https://i1.mopimg.cn/img/tt/2015-11/412/20151130171142892.jpg790x600.jpg",
		"similarUrlFirst": null,
		"similarUrlSecond": null,
		"width": "700",
		"height": "1003",
		"speedrank": null,
		"summarytype": "NormalSummary",
		"ori_pic_url": "http://i1.mopimg.cn/img/tt/2015-11/412/20151130171142892.jpg790x600.jpg",
		"https_convert": "1",
		"imgkey1": "00804db604b24923",
		"imgkey2": "63434bee167457b7",
		"imgcolor": "191",
		"hittag": "0",
		"thumb_width": "250",
		"thumb_height": "359",
		"anchor": null,
		"alt": null,
		"title2": null,
		"title1": "",
		"surr1": null,
		"surr2": "",
		"summarypc": "0",
		"mf_id": "b0ab029bc46a1944",
		"sohu_image": "",
		"lastmodified": "",
		"downloadPath": null,
		"downloadNum": null,
		"siteName": null,
		"anchor1": null,
		"grouppic": 1,
		"biaoqing": 0,
		"gifpic": 0,
		"ch_site_name": "猫扑贴贴论坛",
		"grpdocs": null,
		"grpdata": null,
		"simdata": null,
		"feeddata": null,
		"gifdata": null,
		"pptdata": null,
		"pic_url_noredirect": "https://i1.mopimg.cn/img/tt/2015-11/412/20151130171142892.jpg790x600.jpg",
		"base_url": "",
		"groupid": null,
		"groupsize": 0,
		"easter": false,
		"easterUrl": null,
		"oriTitle": "美女御姐顾欣怡清凉透视装",
		"showSnapShot": false,
		"normalSummary": true,
		"fastSummary": false,
		"allSummary": false,
		"ldata": "1478229060",
		"uri": ""
	}, {
		"type": -1,
		"cacheIndex": 34,
		"title": "中国的哪里盛产美女最多",
		"markedTitle": "中国的哪里盛产美女最多",
		"url": null,
		"summary": null,
		"markedSummary": null,
		"size": "54928",
		"date": null,
		"encoding": null,
		"time": 0,
		"docid": "abe1eea3ca79fc28-c577ebdcb0f3dbcc-5946ad05943a1c3e9ea5ca71033aacad",
		"debugInfo": null,
		"thumbUrl": "https://i03piccdn.sogoucdn.com/b307cd1bbd39f50d",
		"smallThumbUrl": "https://i03piccdn.sogoucdn.com/b307cd1bbd39f50d_tiny",
		"dataType": "pic",
		"page_url": "http://www.qqski.com/help/161901168.html",
		"pic_url": "https://5b0988e595225.cdn.sohucs.com/q_mini,c_zoom,w_640/images/20170801/c0768f56154a4fc688c770901973c0ad.jpeg",
		"similarUrlFirst": null,
		"similarUrlSecond": null,
		"width": "600",
		"height": "393",
		"speedrank": null,
		"summarytype": "NormalSummary",
		"ori_pic_url": "http://5b0988e595225.cdn.sohucs.com/q_mini,c_zoom,w_640/images/20170801/c0768f56154a4fc688c770901973c0ad.jpeg",
		"https_convert": "1",
		"imgkey1": "00f03e550275ca54",
		"imgkey2": "e25087bb02213433",
		"imgcolor": "174",
		"hittag": "0",
		"thumb_width": "381",
		"thumb_height": "250",
		"anchor": null,
		"alt": null,
		"title2": null,
		"title1": "",
		"surr1": null,
		"surr2": "俄罗斯盛产美女 中国盛产美女之城top10 曝全球15大盛产美女城市 _中国网 乌克兰盛产美女且男女比例失衡, 那么多出来的那部分美女去了哪里? 揭开俄罗斯盛产美女的秘密",
		"summarypc": "0",
		"mf_id": "b307cd1bbd39f50d",
		"sohu_image": "",
		"lastmodified": "",
		"downloadPath": null,
		"downloadNum": null,
		"siteName": null,
		"anchor1": null,
		"grouppic": 0,
		"biaoqing": 0,
		"gifpic": 0,
		"ch_site_name": "斯卡依头像乐园",
		"grpdocs": null,
		"grpdata": null,
		"simdata": null,
		"feeddata": null,
		"gifdata": null,
		"pptdata": null,
		"pic_url_noredirect": "https://5b0988e595225.cdn.sohucs.com/q_mini,c_zoom,w_640/images/20170801/c0768f56154a4fc688c770901973c0ad.jpeg",
		"base_url": "",
		"groupid": null,
		"groupsize": 0,
		"easter": false,
		"easterUrl": null,
		"oriTitle": "中国的哪里盛产美女最多",
		"showSnapShot": false,
		"normalSummary": true,
		"fastSummary": false,
		"allSummary": false,
		"ldata": "1534512936",
		"uri": ""
	}, {
		"type": -1,
		"cacheIndex": 35,
		"title": "美女 乳 此多娇 令无数英雄尽折腰",
		"markedTitle": "美女 乳 此多娇 令无数英雄尽折腰",
		"url": null,
		"summary": null,
		"markedSummary": null,
		"size": "129823",
		"date": null,
		"encoding": null,
		"time": 0,
		"docid": "e7d4cac126941b5a-81e8e7ce0eb46d21-e3ed55094d5ee6996fbc2a89a311ff26",
		"debugInfo": null,
		"thumbUrl": "https://i02piccdn.sogoucdn.com/834c8e80cbc2f37f",
		"smallThumbUrl": "https://i02piccdn.sogoucdn.com/834c8e80cbc2f37f_tiny",
		"dataType": "pic",
		"page_url": "http://bbs.zol.com.cn/sjbbs/d297_407407.html",
		"pic_url": "https://i1.bbs.fd.zol-img.com.cn/t_s800x5000/g4/M00/05/0D/Cg-4WVFKCh6IE0kIAANILw0BKRYAAGWsQNr7sQAA0hH421.jpg",
		"similarUrlFirst": null,
		"similarUrlSecond": null,
		"width": "800",
		"height": "1200",
		"speedrank": null,
		"summarytype": "NormalSummary",
		"ori_pic_url": "http://i1.bbs.fd.zol-img.com.cn/t_s800x5000/g4/M00/05/0D/Cg-4WVFKCh6IE0kIAANILw0BKRYAAGWsQNr7sQAA0hH421.jpg",
		"https_convert": "1",
		"imgkey1": "036c21ff0495b6db",
		"imgkey2": "c02d4e69865a367b",
		"imgcolor": "128",
		"hittag": "0",
		"thumb_width": "250",
		"thumb_height": "374",
		"anchor": null,
		"alt": null,
		"title2": null,
		"title1": "",
		"surr1": null,
		"surr2": "",
		"summarypc": "0",
		"mf_id": "834c8e80cbc2f37f",
		"sohu_image": "",
		"lastmodified": "",
		"downloadPath": null,
		"downloadNum": null,
		"siteName": null,
		"anchor1": null,
		"grouppic": 0,
		"biaoqing": 0,
		"gifpic": 0,
		"ch_site_name": "ZOL论坛",
		"grpdocs": null,
		"grpdata": null,
		"simdata": null,
		"feeddata": null,
		"gifdata": null,
		"pptdata": null,
		"pic_url_noredirect": "https://i1.bbs.fd.zol-img.com.cn/t_s800x5000/g4/M00/05/0D/Cg-4WVFKCh6IE0kIAANILw0BKRYAAGWsQNr7sQAA0hH421.jpg",
		"base_url": "",
		"groupid": null,
		"groupsize": 0,
		"easter": false,
		"easterUrl": null,
		"oriTitle": "美女 乳 此多娇 令无数英雄尽折腰",
		"showSnapShot": false,
		"normalSummary": true,
		"fastSummary": false,
		"allSummary": false,
		"ldata": "1512385585",
		"uri": ""
	}, {
		"type": -1,
		"cacheIndex": 36,
		"title": "揭秘全球顶级美女富豪奢华生活",
		"markedTitle": "揭秘全球顶级美女富豪奢华生活",
		"url": null,
		"summary": null,
		"markedSummary": null,
		"size": "43540",
		"date": null,
		"encoding": null,
		"time": 0,
		"docid": "5f1f7f598fa8887b-a8a7b506b3e4e419-288561068544e85c57f9724fd03adaea",
		"debugInfo": null,
		"thumbUrl": "https://i01piccdn.sogoucdn.com/b26a3801482699a1",
		"smallThumbUrl": "https://i01piccdn.sogoucdn.com/b26a3801482699a1_tiny",
		"dataType": "pic",
		"page_url": "http://www.studentboss.com/html/news/2012-07-24/118194.htm?bsh_bid=110867828",
		"pic_url": "http://www.studentboss.com/uploadfile/20120724/20120724012807482.jpg",
		"similarUrlFirst": null,
		"similarUrlSecond": null,
		"width": "450",
		"height": "464",
		"speedrank": null,
		"summarytype": "NormalSummary",
		"ori_pic_url": "http://www.studentboss.com/uploadfile/20120724/20120724012807482.jpg",
		"https_convert": "0",
		"imgkey1": "01783e00026ac608",
		"imgkey2": "8790862360b3201d",
		"imgcolor": "191",
		"hittag": "0",
		"thumb_width": "252",
		"thumb_height": "259",
		"anchor": null,
		"alt": null,
		"title2": null,
		"title1": "",
		"surr1": null,
		"surr2": "伊万卡·特朗普 (Ivanka Trump) 既继承了妈妈的美丽,又是爸爸巨额财富的惟一继承者.在这个拥有豪华游艇、一座有140个房间的豪华别墅和21亿美元继承权的女孩身上,没有一点娇生惯养的坏毛病.在她29年的平坦\"钱途\"上,有30%是借了家族的\"光\",",
		"summarypc": "0",
		"mf_id": "b26a3801482699a1",
		"sohu_image": "",
		"lastmodified": "",
		"downloadPath": null,
		"downloadNum": null,
		"siteName": null,
		"anchor1": null,
		"grouppic": 1,
		"biaoqing": 0,
		"gifpic": 0,
		"ch_site_name": "中国大学生创业网",
		"grpdocs": null,
		"grpdata": null,
		"simdata": null,
		"feeddata": null,
		"gifdata": null,
		"pptdata": null,
		"pic_url_noredirect": "http://www.studentboss.com/uploadfile/20120724/20120724012807482.jpg",
		"base_url": "",
		"groupid": null,
		"groupsize": 0,
		"easter": false,
		"easterUrl": null,
		"oriTitle": "揭秘全球顶级美女富豪奢华生活",
		"showSnapShot": false,
		"normalSummary": true,
		"fastSummary": false,
		"allSummary": false,
		"ldata": "1493779057",
		"uri": ""
	}, {
		"type": -1,
		"cacheIndex": 37,
		"title": "性感美女图片",
		"markedTitle": "性感美女图片",
		"url": null,
		"summary": null,
		"markedSummary": null,
		"size": "95804",
		"date": null,
		"encoding": null,
		"time": 0,
		"docid": "ac75323d6b6de243-eac8ca492ea27a6f-bb6889a40105b329ca66eb132fb30c5a",
		"debugInfo": null,
		"thumbUrl": "https://i02piccdn.sogoucdn.com/e5cb51d557d69003",
		"smallThumbUrl": "https://i02piccdn.sogoucdn.com/e5cb51d557d69003_tiny",
		"dataType": "pic",
		"page_url": "http://www.nipic.com/show/1/14/8a0069f669ea468b.html",
		"pic_url": "http://pic7.nipic.com/20100523/1304280_082340087802_2.jpg",
		"similarUrlFirst": null,
		"similarUrlSecond": null,
		"width": "683",
		"height": "1024",
		"speedrank": null,
		"summarytype": "NormalSummary",
		"ori_pic_url": "http://pic7.nipic.com/20100523/1304280_082340087802_2.jpg",
		"https_convert": "0",
		"imgkey1": "03681fb606db6df6",
		"imgkey2": "70736a44a7424bcf",
		"imgcolor": "231",
		"hittag": "0",
		"thumb_width": "250",
		"thumb_height": "374",
		"anchor": null,
		"alt": null,
		"title2": null,
		"title1": "",
		"surr1": null,
		"surr2": "",
		"summarypc": "0",
		"mf_id": "e5cb51d557d69003",
		"sohu_image": "",
		"lastmodified": "",
		"downloadPath": null,
		"downloadNum": null,
		"siteName": null,
		"anchor1": null,
		"grouppic": 0,
		"biaoqing": 0,
		"gifpic": 0,
		"ch_site_name": "昵图网",
		"grpdocs": null,
		"grpdata": null,
		"simdata": null,
		"feeddata": null,
		"gifdata": null,
		"pptdata": null,
		"pic_url_noredirect": "http://pic7.nipic.com/20100523/1304280_082340087802_2.jpg",
		"base_url": "",
		"groupid": null,
		"groupsize": 0,
		"easter": false,
		"easterUrl": null,
		"oriTitle": "性感美女图片",
		"showSnapShot": false,
		"normalSummary": true,
		"fastSummary": false,
		"allSummary": false,
		"ldata": "1478688012",
		"uri": ""
	}, {
		"type": -1,
		"cacheIndex": 38,
		"title": "性感美女图片",
		"markedTitle": "性感美女图片",
		"url": null,
		"summary": null,
		"markedSummary": null,
		"size": "128215",
		"date": null,
		"encoding": null,
		"time": 0,
		"docid": "ac75323d6b6de243-6a288fb2bd195a34-2e51acfe2aeab2a4069dab49a6784c24",
		"debugInfo": null,
		"thumbUrl": "https://i01piccdn.sogoucdn.com/5547728209a9678a",
		"smallThumbUrl": "https://i01piccdn.sogoucdn.com/5547728209a9678a_tiny",
		"dataType": "pic",
		"page_url": "http://www.nipic.com/show/1/68/3960478k38c1809b.html",
		"pic_url": "http://pic11.nipic.com/20101123/6058161_132622002276_2.jpg",
		"similarUrlFirst": null,
		"similarUrlSecond": null,
		"width": "1024",
		"height": "683",
		"speedrank": null,
		"summarytype": "NormalSummary",
		"ori_pic_url": "http://pic11.nipic.com/20101123/6058161_132622002276_2.jpg",
		"https_convert": "0",
		"imgkey1": "03402dff06db59b5",
		"imgkey2": "55fab6ac07a64940",
		"imgcolor": "128",
		"hittag": "0",
		"thumb_width": "374",
		"thumb_height": "250",
		"anchor": null,
		"alt": null,
		"title2": null,
		"title1": "",
		"surr1": null,
		"surr2": "",
		"summarypc": "0",
		"mf_id": "5547728209a9678a",
		"sohu_image": "",
		"lastmodified": "",
		"downloadPath": null,
		"downloadNum": null,
		"siteName": null,
		"anchor1": null,
		"grouppic": 0,
		"biaoqing": 0,
		"gifpic": 0,
		"ch_site_name": "昵图网",
		"grpdocs": null,
		"grpdata": null,
		"simdata": null,
		"feeddata": null,
		"gifdata": null,
		"pptdata": null,
		"pic_url_noredirect": "http://pic11.nipic.com/20101123/6058161_132622002276_2.jpg",
		"base_url": "",
		"groupid": null,
		"groupsize": 0,
		"easter": false,
		"easterUrl": null,
		"oriTitle": "性感美女图片",
		"showSnapShot": false,
		"normalSummary": true,
		"fastSummary": false,
		"allSummary": false,
		"ldata": "1487080307",
		"uri": ""
	}, {
		"type": -1,
		"cacheIndex": 39,
		"title": "上戏 美女 倪歆柔图片",
		"markedTitle": "上戏 美女 倪歆柔图片",
		"url": null,
		"summary": null,
		"markedSummary": null,
		"size": "121460",
		"date": null,
		"encoding": null,
		"time": 0,
		"docid": "ac75323d6b6de243-6a8470ba18ff4002-f94a5b527e68f5f66e8a84855e8476c7",
		"debugInfo": null,
		"thumbUrl": "https://i03piccdn.sogoucdn.com/bcab58d3f7e8894f",
		"smallThumbUrl": "https://i03piccdn.sogoucdn.com/bcab58d3f7e8894f_tiny",
		"dataType": "pic",
		"page_url": "http://www.nipic.com/show/3860736.html",
		"pic_url": "http://pic10.nipic.com/20101101/3970232_121520009210_2.jpg",
		"similarUrlFirst": null,
		"similarUrlSecond": null,
		"width": "683",
		"height": "1024",
		"speedrank": null,
		"summarytype": "NormalSummary",
		"ori_pic_url": "http://pic10.nipic.com/20101101/3970232_121520009210_2.jpg",
		"https_convert": "0",
		"imgkey1": "036c1bff06b637b5",
		"imgkey2": "f252d68d0f617599",
		"imgcolor": "231",
		"hittag": "0",
		"thumb_width": "250",
		"thumb_height": "374",
		"anchor": null,
		"alt": null,
		"title2": null,
		"title1": "",
		"surr1": null,
		"surr2": "",
		"summarypc": "0",
		"mf_id": "bcab58d3f7e8894f",
		"sohu_image": "",
		"lastmodified": "",
		"downloadPath": null,
		"downloadNum": null,
		"siteName": null,
		"anchor1": null,
		"grouppic": 0,
		"biaoqing": 0,
		"gifpic": 0,
		"ch_site_name": "昵图网",
		"grpdocs": null,
		"grpdata": null,
		"simdata": null,
		"feeddata": null,
		"gifdata": null,
		"pptdata": null,
		"pic_url_noredirect": "http://pic10.nipic.com/20101101/3970232_121520009210_2.jpg",
		"base_url": "",
		"groupid": null,
		"groupsize": 0,
		"easter": false,
		"easterUrl": null,
		"oriTitle": "上戏 美女 倪歆柔图片",
		"showSnapShot": false,
		"normalSummary": true,
		"fastSummary": false,
		"allSummary": false,
		"ldata": "1521439315",
		"uri": ""
	}, {
		"type": -1,
		"cacheIndex": 40,
		"title": "美女广告模特图片",
		"markedTitle": "美女广告模特图片",
		"url": null,
		"summary": null,
		"markedSummary": null,
		"size": "134970",
		"date": null,
		"encoding": null,
		"time": 0,
		"docid": "ac75323d6b6de243-c361eb70e2169653-594f0ce0d191df750ba1165fd1ded6f3",
		"debugInfo": null,
		"thumbUrl": "https://i02piccdn.sogoucdn.com/9202f4bbc914dbbd",
		"smallThumbUrl": "https://i02piccdn.sogoucdn.com/9202f4bbc914dbbd_tiny",
		"dataType": "pic",
		"page_url": "http://www.nipic.com/show/1/14/68e88f7ab9909bfa.html",
		"pic_url": "http://pic4.nipic.com/20091024/3481385_082531077475_2.jpg",
		"similarUrlFirst": null,
		"similarUrlSecond": null,
		"width": "1024",
		"height": "640",
		"speedrank": null,
		"summarytype": "NormalSummary",
		"ori_pic_url": "http://pic4.nipic.com/20091024/3481385_082531077475_2.jpg",
		"https_convert": "0",
		"imgkey1": "01683489034a34d2",
		"imgkey2": "ddc309b0d79e2b45",
		"imgcolor": "128",
		"hittag": "0",
		"thumb_width": "399",
		"thumb_height": "250",
		"anchor": null,
		"alt": null,
		"title2": null,
		"title1": "",
		"surr1": null,
		"surr2": "",
		"summarypc": "0",
		"mf_id": "9202f4bbc914dbbd",
		"sohu_image": "",
		"lastmodified": "",
		"downloadPath": null,
		"downloadNum": null,
		"siteName": null,
		"anchor1": null,
		"grouppic": 0,
		"biaoqing": 0,
		"gifpic": 0,
		"ch_site_name": "昵图网",
		"grpdocs": null,
		"grpdata": null,
		"simdata": null,
		"feeddata": null,
		"gifdata": null,
		"pptdata": null,
		"pic_url_noredirect": "http://pic4.nipic.com/20091024/3481385_082531077475_2.jpg",
		"base_url": "",
		"groupid": null,
		"groupsize": 0,
		"easter": false,
		"easterUrl": null,
		"oriTitle": "美女广告模特图片",
		"showSnapShot": false,
		"normalSummary": true,
		"fastSummary": false,
		"allSummary": false,
		"ldata": "1472993358",
		"uri": ""
	}, {
		"type": -1,
		"cacheIndex": 41,
		"title": "游戏美女叶梓萱用黑丝与白丝诠释绝美性感",
		"markedTitle": "游戏美女叶梓萱用黑丝与白丝诠释绝美性感",
		"url": null,
		"summary": null,
		"markedSummary": null,
		"size": "41888",
		"date": null,
		"encoding": null,
		"time": 0,
		"docid": "e7d4cac126941b5a-46adc2a9f66634ca-23d21d8a5433a2e0c29d86444af12543",
		"debugInfo": null,
		"thumbUrl": "https://i01piccdn.sogoucdn.com/3f9bf9db47e994cd",
		"smallThumbUrl": "https://i01piccdn.sogoucdn.com/3f9bf9db47e994cd_tiny",
		"dataType": "pic",
		"page_url": "http://game.zol.com.cn/slide/349/3491699_1.html",
		"pic_url": "https://2f.zol-img.com.cn/product/105_940x705/927/ce5j8QTZq2hpI.jpg",
		"similarUrlFirst": null,
		"similarUrlSecond": null,
		"width": "498",
		"height": "705",
		"speedrank": null,
		"summarytype": "NormalSummary",
		"ori_pic_url": "http://2f.zol-img.com.cn/product/105_940x705/927/ce5j8QTZq2hpI.jpg",
		"https_convert": "1",
		"imgkey1": "05c41fff07db49ff",
		"imgkey2": "7a7bc45c0d0e91ea",
		"imgcolor": "231",
		"hittag": "0",
		"thumb_width": "249",
		"thumb_height": "353",
		"anchor": null,
		"alt": null,
		"title2": null,
		"title1": "",
		"surr1": null,
		"surr2": "游戏美女叶梓萱用黑丝与白丝诠释绝美性感 重新播放",
		"summarypc": "0",
		"mf_id": "3f9bf9db47e994cd",
		"sohu_image": "",
		"lastmodified": "",
		"downloadPath": null,
		"downloadNum": null,
		"siteName": null,
		"anchor1": null,
		"grouppic": 1,
		"biaoqing": 0,
		"gifpic": 0,
		"ch_site_name": "中关村在线",
		"grpdocs": null,
		"grpdata": null,
		"simdata": null,
		"feeddata": null,
		"gifdata": null,
		"pptdata": null,
		"pic_url_noredirect": "https://2f.zol-img.com.cn/product/105_940x705/927/ce5j8QTZq2hpI.jpg",
		"base_url": "",
		"groupid": null,
		"groupsize": 0,
		"easter": false,
		"easterUrl": null,
		"oriTitle": "游戏美女叶梓萱用黑丝与白丝诠释绝美性感",
		"showSnapShot": false,
		"normalSummary": true,
		"fastSummary": false,
		"allSummary": false,
		"ldata": "1517460017",
		"uri": ""
	}, {
		"type": -1,
		"cacheIndex": 42,
		"title": "全国各省第一美女最新出炉",
		"markedTitle": "全国各省第一美女最新出炉",
		"url": null,
		"summary": null,
		"markedSummary": null,
		"size": "126203",
		"date": null,
		"encoding": null,
		"time": 0,
		"docid": "8af4ad3e34aa1a12-581860e0973c9003-183b747cc91be6df256aba1c922fd269",
		"debugInfo": null,
		"thumbUrl": "https://i04piccdn.sogoucdn.com/9b652f48793a51fd",
		"smallThumbUrl": "https://i04piccdn.sogoucdn.com/9b652f48793a51fd_tiny",
		"dataType": "pic",
		"page_url": "http://www.luaninfo.com/News/ent/2007/10/05/08011753119.html",
		"pic_url": "https://www.luaninfo.com/UploadFiles/News_UploadFiles_6955/200710/20071005080307587.jpg",
		"similarUrlFirst": null,
		"similarUrlSecond": null,
		"width": "500",
		"height": "706",
		"speedrank": null,
		"summarytype": "NormalSummary",
		"ori_pic_url": "http://www.luaninfo.com/UploadFiles/News_UploadFiles_6955/200710/20071005080307587.jpg",
		"https_convert": "1",
		"imgkey1": "03083fff05b36b64",
		"imgkey2": "f7dd2cf2acb08740",
		"imgcolor": "128",
		"hittag": "0",
		"thumb_width": "250",
		"thumb_height": "352",
		"anchor": null,
		"alt": null,
		"title2": null,
		"title1": "",
		"surr1": null,
		"surr2": "浙江——周迅 江西——陈红",
		"summarypc": "0",
		"mf_id": "9b652f48793a51fd",
		"sohu_image": "",
		"lastmodified": "",
		"downloadPath": null,
		"downloadNum": null,
		"siteName": null,
		"anchor1": null,
		"grouppic": 0,
		"biaoqing": 0,
		"gifpic": 0,
		"ch_site_name": "六安新闻网",
		"grpdocs": null,
		"grpdata": null,
		"simdata": null,
		"feeddata": null,
		"gifdata": null,
		"pptdata": null,
		"pic_url_noredirect": "https://www.luaninfo.com/UploadFiles/News_UploadFiles_6955/200710/20071005080307587.jpg",
		"base_url": "",
		"groupid": null,
		"groupsize": 0,
		"easter": false,
		"easterUrl": null,
		"oriTitle": "全国各省第一美女最新出炉",
		"showSnapShot": false,
		"normalSummary": true,
		"fastSummary": false,
		"allSummary": false,
		"ldata": "1338725536",
		"uri": ""
	}, {
		"type": -1,
		"cacheIndex": 43,
		"title": "日本90后美女泳装写真 清凉性感笑容温婉",
		"markedTitle": "日本90后美女泳装写真 清凉性感笑容温婉",
		"url": null,
		"summary": null,
		"markedSummary": null,
		"size": "288359",
		"date": null,
		"encoding": null,
		"time": 0,
		"docid": "d7036c9a17f5fda2-4b551764bc9fc42d-38be12e7b97da12c45e90885590d11f7",
		"debugInfo": null,
		"thumbUrl": "https://i01piccdn.sogoucdn.com/e0b80394e912c4f6",
		"smallThumbUrl": "https://i01piccdn.sogoucdn.com/e0b80394e912c4f6_tiny",
		"dataType": "pic",
		"page_url": "http://slide.eladies.sina.com.cn/news/slide_3_77542_26706.html?img=377939",
		"pic_url": "https://www.sinaimg.cn/dy/slidenews/3_img/2016_20/77542_377937_789222.jpg",
		"similarUrlFirst": null,
		"similarUrlSecond": null,
		"width": "950",
		"height": "1362",
		"speedrank": null,
		"summarytype": "NormalSummary",
		"ori_pic_url": "http://www.sinaimg.cn/dy/slidenews/3_img/2016_20/77542_377937_789222.jpg",
		"https_convert": "1",
		"imgkey1": "01543bff06b6ebad",
		"imgkey2": "aa10d70f5970f438",
		"imgcolor": "211",
		"hittag": "0",
		"thumb_width": "250",
		"thumb_height": "359",
		"anchor": null,
		"alt": null,
		"title2": null,
		"title1": "",
		"surr1": null,
		"surr2": "",
		"summarypc": "0",
		"mf_id": "e0b80394e912c4f6",
		"sohu_image": "",
		"lastmodified": "",
		"downloadPath": null,
		"downloadNum": null,
		"siteName": null,
		"anchor1": null,
		"grouppic": 0,
		"biaoqing": 0,
		"gifpic": 0,
		"ch_site_name": "新浪图片",
		"grpdocs": null,
		"grpdata": null,
		"simdata": null,
		"feeddata": null,
		"gifdata": null,
		"pptdata": null,
		"pic_url_noredirect": "https://www.sinaimg.cn/dy/slidenews/3_img/2016_20/77542_377937_789222.jpg",
		"base_url": "",
		"groupid": null,
		"groupsize": 0,
		"easter": false,
		"easterUrl": null,
		"oriTitle": "日本90后美女泳装写真 清凉性感笑容温婉",
		"showSnapShot": false,
		"normalSummary": true,
		"fastSummary": false,
		"allSummary": false,
		"ldata": "1491730955",
		"uri": ""
	}, {
		"type": -1,
		"cacheIndex": 44,
		"title": "红唇美女风情显爆乳和好身材",
		"markedTitle": "红唇美女风情显爆乳和好身材",
		"url": null,
		"summary": null,
		"markedSummary": null,
		"size": "134613",
		"date": null,
		"encoding": null,
		"time": 0,
		"docid": "e7d4cac126941b5a-4584a00622eb3806-fc5239c12c6998b6afa9d05dbde8904c",
		"debugInfo": null,
		"thumbUrl": "https://i03piccdn.sogoucdn.com/8a2bfbed25c2c17e",
		"smallThumbUrl": "https://i03piccdn.sogoucdn.com/8a2bfbed25c2c17e_tiny",
		"dataType": "pic",
		"page_url": "http://bbs.zol.com.cn/dcbbs/d16_436220.html",
		"pic_url": "https://i4.bbswater.fd.zol-img.com.cn/t_s1200x5000/g5/M00/05/0E/ChMkJlbMePKIMONIAAIMXFNVoF0AALWVAJYLz4AAgx0554.jpg",
		"similarUrlFirst": null,
		"similarUrlSecond": null,
		"width": "700",
		"height": "1030",
		"speedrank": null,
		"summarytype": "NormalSummary",
		"ori_pic_url": "http://i4.bbswater.fd.zol-img.com.cn/t_s1200x5000/g5/M00/05/0E/ChMkJlbMePKIMONIAAIMXFNVoF0AALWVAJYLz4AAgx0554.jpg",
		"https_convert": "1",
		"imgkey1": "024c39ff06b5b7f5",
		"imgkey2": "53eb5c3c859643e8",
		"imgcolor": "212",
		"hittag": "0",
		"thumb_width": "250",
		"thumb_height": "367",
		"anchor": null,
		"alt": null,
		"title2": null,
		"title1": "",
		"surr1": null,
		"surr2": "",
		"summarypc": "0",
		"mf_id": "8a2bfbed25c2c17e",
		"sohu_image": "",
		"lastmodified": "",
		"downloadPath": null,
		"downloadNum": null,
		"siteName": null,
		"anchor1": null,
		"grouppic": 0,
		"biaoqing": 0,
		"gifpic": 0,
		"ch_site_name": "ZOL论坛",
		"grpdocs": null,
		"grpdata": null,
		"simdata": null,
		"feeddata": null,
		"gifdata": null,
		"pptdata": null,
		"pic_url_noredirect": "https://i4.bbswater.fd.zol-img.com.cn/t_s1200x5000/g5/M00/05/0E/ChMkJlbMePKIMONIAAIMXFNVoF0AALWVAJYLz4AAgx0554.jpg",
		"base_url": "",
		"groupid": null,
		"groupsize": 0,
		"easter": false,
		"easterUrl": null,
		"oriTitle": "红唇美女风情显爆乳和好身材",
		"showSnapShot": false,
		"normalSummary": true,
		"fastSummary": false,
		"allSummary": false,
		"ldata": "1481892851",
		"uri": ""
	}, {
		"type": -1,
		"cacheIndex": 45,
		"title": "高雅性感美女",
		"markedTitle": "高雅性感美女",
		"url": null,
		"summary": null,
		"markedSummary": null,
		"size": "30467",
		"date": null,
		"encoding": null,
		"time": 0,
		"docid": "6dfb2f34eed2f074-eb079ee68cf5a8cc-9c621b63f33c4dfeceb6367f4296cb5e",
		"debugInfo": null,
		"thumbUrl": "https://i03piccdn.sogoucdn.com/8c6e7df68f340b31",
		"smallThumbUrl": "https://i03piccdn.sogoucdn.com/8c6e7df68f340b31_tiny",
		"dataType": "pic",
		"page_url": "http://bbs.voc.com.cn/viewthread.php?tid=2248156",
		"pic_url": "http://image.hnol.net/c/2010-03/06/17/201003061755188314-2381913.jpg",
		"similarUrlFirst": null,
		"similarUrlSecond": null,
		"width": "800",
		"height": "531",
		"speedrank": null,
		"summarytype": "NormalSummary",
		"ori_pic_url": "http://image.hnol.net/c/2010-03/06/17/201003061755188314-2381913.jpg",
		"https_convert": "0",
		"imgkey1": "033019ff07fe4924",
		"imgkey2": "74e57e488724039b",
		"imgcolor": "231",
		"hittag": "0",
		"thumb_width": "379",
		"thumb_height": "250",
		"anchor": null,
		"alt": null,
		"title2": null,
		"title1": "",
		"surr1": null,
		"surr2": "",
		"summarypc": "0",
		"mf_id": "8c6e7df68f340b31",
		"sohu_image": "",
		"lastmodified": "",
		"downloadPath": null,
		"downloadNum": null,
		"siteName": null,
		"anchor1": null,
		"grouppic": 0,
		"biaoqing": 0,
		"gifpic": 0,
		"ch_site_name": "华声论坛",
		"grpdocs": null,
		"grpdata": null,
		"simdata": null,
		"feeddata": null,
		"gifdata": null,
		"pptdata": null,
		"pic_url_noredirect": "http://image.hnol.net/c/2010-03/06/17/201003061755188314-2381913.jpg",
		"base_url": "",
		"groupid": null,
		"groupsize": 0,
		"easter": false,
		"easterUrl": null,
		"oriTitle": "高雅性感美女",
		"showSnapShot": false,
		"normalSummary": true,
		"fastSummary": false,
		"allSummary": false,
		"ldata": "1516013384",
		"uri": ""
	}, {
		"type": -1,
		"cacheIndex": 46,
		"title": "韩国美女 申世荷",
		"markedTitle": "韩国美女 申世荷",
		"url": null,
		"summary": null,
		"markedSummary": null,
		"size": "179716",
		"date": null,
		"encoding": null,
		"time": 0,
		"docid": "6dfb2f34eed2f074-eb079ee68cf5a8cc-88d6db48e3e2503eef6a59e532a55e96",
		"debugInfo": null,
		"thumbUrl": "https://i03piccdn.sogoucdn.com/dcb7150ab4cb41d9",
		"smallThumbUrl": "https://i03piccdn.sogoucdn.com/dcb7150ab4cb41d9_tiny",
		"dataType": "pic",
		"page_url": "http://bbs.voc.com.cn/mm/meinv-5458082-5-1.html",
		"pic_url": "http://image.hnol.net/c/2013-08/30/22/201308302228288473-2381913.jpg",
		"similarUrlFirst": null,
		"similarUrlSecond": null,
		"width": "1024",
		"height": "1536",
		"speedrank": null,
		"summarytype": "NormalSummary",
		"ori_pic_url": "http://image.hnol.net/c/2013-08/30/22/201308302228288473-2381913.jpg",
		"https_convert": "0",
		"imgkey1": "016c216e06dedb76",
		"imgkey2": "746f76ce0b648383",
		"imgcolor": "134",
		"hittag": "0",
		"thumb_width": "250",
		"thumb_height": "374",
		"anchor": null,
		"alt": null,
		"title2": null,
		"title1": "",
		"surr1": null,
		"surr2": "",
		"summarypc": "0",
		"mf_id": "dcb7150ab4cb41d9",
		"sohu_image": "",
		"lastmodified": "",
		"downloadPath": null,
		"downloadNum": null,
		"siteName": null,
		"anchor1": null,
		"grouppic": 0,
		"biaoqing": 0,
		"gifpic": 0,
		"ch_site_name": "华声论坛",
		"grpdocs": null,
		"grpdata": null,
		"simdata": null,
		"feeddata": null,
		"gifdata": null,
		"pptdata": null,
		"pic_url_noredirect": "http://image.hnol.net/c/2013-08/30/22/201308302228288473-2381913.jpg",
		"base_url": "",
		"groupid": null,
		"groupsize": 0,
		"easter": false,
		"easterUrl": null,
		"oriTitle": "韩国美女 申世荷",
		"showSnapShot": false,
		"normalSummary": true,
		"fastSummary": false,
		"allSummary": false,
		"ldata": "1484390515",
		"uri": ""
	}, {
		"type": -1,
		"cacheIndex": 47,
		"title": "美女图图片",
		"markedTitle": "美女图图片",
		"url": null,
		"summary": null,
		"markedSummary": null,
		"size": "135422",
		"date": null,
		"encoding": null,
		"time": 0,
		"docid": "ac75323d6b6de243-a58ff320b7144183-90ad1510122822f6d2c8233585919ebf",
		"debugInfo": null,
		"thumbUrl": "https://i03piccdn.sogoucdn.com/3c8aa92144ab4393",
		"smallThumbUrl": "https://i03piccdn.sogoucdn.com/3c8aa92144ab4393_tiny",
		"dataType": "pic",
		"page_url": "http://www.nipic.com/show/1/68/8344502ka6354855.html",
		"pic_url": "http://pic30.nipic.com/20130625/2929309_165603377149_2.jpg",
		"similarUrlFirst": null,
		"similarUrlSecond": null,
		"width": "683",
		"height": "1024",
		"speedrank": null,
		"summarytype": "NormalSummary",
		"ori_pic_url": "http://pic30.nipic.com/20130625/2929309_165603377149_2.jpg",
		"https_convert": "0",
		"imgkey1": "03c01bff07dbdbf5",
		"imgkey2": "5163b42e0f148348",
		"imgcolor": "128",
		"hittag": "0",
		"thumb_width": "250",
		"thumb_height": "374",
		"anchor": null,
		"alt": null,
		"title2": null,
		"title1": "",
		"surr1": null,
		"surr2": "",
		"summarypc": "0",
		"mf_id": "3c8aa92144ab4393",
		"sohu_image": "",
		"lastmodified": "",
		"downloadPath": null,
		"downloadNum": null,
		"siteName": null,
		"anchor1": null,
		"grouppic": 0,
		"biaoqing": 0,
		"gifpic": 0,
		"ch_site_name": "昵图网",
		"grpdocs": null,
		"grpdata": null,
		"simdata": null,
		"feeddata": null,
		"gifdata": null,
		"pptdata": null,
		"pic_url_noredirect": "http://pic30.nipic.com/20130625/2929309_165603377149_2.jpg",
		"base_url": "",
		"groupid": null,
		"groupsize": 0,
		"easter": false,
		"easterUrl": null,
		"oriTitle": "美女图图片",
		"showSnapShot": false,
		"normalSummary": true,
		"fastSummary": false,
		"allSummary": false,
		"ldata": "1494377620",
		"uri": ""
	}]
}